{"v":"5.9.0","fr":60,"ip":0,"op":120,"w":403,"h":300,"nm":"Transform","ddd":0,"assets":[],"layers":[{"ddd":0,"ind":1,"ty":4,"nm":"Transform","sr":1,"ks":{"o":{"a":0,"k":100,"ix":11},"r":{"a":0,"k":0,"ix":10},"p":{"a":0,"k":[200.569,150,0],"ix":2,"l":2},"a":{"a":0,"k":[0,0,0],"ix":1,"l":2},"s":{"a":0,"k":[100,100,100],"ix":6,"l":2}},"ao":0,"shapes":[{"ty":"rc","d":1,"s":{"a":0,"k":[401.137,298],"ix":2},"p":{"a":0,"k":[0,0],"ix":3},"r":{"a":0,"k":0,"ix":4},"nm":"Rectangle Path 1","mn":"ADBE Vector Shape - Rect","hd":false}],"ip":0,"op":3600,"st":0,"bm":0},{"ddd":0,"ind":2,"ty":4,"nm":"Path 2707","parent":1,"sr":1,"ks":{"o":{"a":0,"k":100,"ix":11},"r":{"a":0,"k":0,"ix":10},"p":{"a":0,"k":[3.349,-132.027,0],"ix":2,"l":2},"a":{"a":0,"k":[8.797,8.798,0],"ix":1,"l":2},"s":{"a":0,"k":[100,100,100],"ix":6,"l":2}},"ao":0,"shapes":[{"ty":"gr","it":[{"ind":0,"ty":"sh","ix":1,"ks":{"a":0,"k":{"i":[[0,-4.859],[4.859,0],[0,4.859],[-4.858,0]],"o":[[0,4.859],[-4.858,0],[0,-4.859],[4.859,0]],"v":[[17.594,8.798],[8.797,17.595],[0,8.798],[8.797,0]],"c":true},"ix":2},"nm":"Path 1","mn":"ADBE Vector Shape - Group","hd":false},{"ty":"st","c":{"a":0,"k":[0.694117647059,0.396078431373,0.290196078431,1],"ix":3},"o":{"a":0,"k":100,"ix":4},"w":{"a":0,"k":1,"ix":5},"lc":1,"lj":1,"ml":4,"bm":0,"nm":"Stroke 1","mn":"ADBE Vector Graphic - Stroke","hd":false},{"ty":"gf","o":{"a":0,"k":100,"ix":10},"r":1,"bm":0,"g":{"p":3,"k":{"a":0,"k":[0,1,0.533,0.376,0.5,1,0.741,0.441,1,1,0.949,0.506],"ix":9}},"s":{"a":0,"k":[10,12],"ix":5},"e":{"a":0,"k":[-17,0.5],"ix":6},"t":1,"nm":"Gradient Fill 1","mn":"ADBE Vector Graphic - G-Fill","hd":false},{"ty":"tr","p":{"a":0,"k":[0,0],"ix":2},"a":{"a":0,"k":[0,0],"ix":1},"s":{"a":0,"k":[100,100],"ix":3},"r":{"a":0,"k":0,"ix":6},"o":{"a":0,"k":100,"ix":7},"sk":{"a":0,"k":0,"ix":4},"sa":{"a":0,"k":0,"ix":5},"nm":"Transform"}],"nm":"Path 2707","np":3,"cix":2,"bm":0,"ix":1,"mn":"ADBE Vector Group","hd":false}],"ip":0,"op":3600,"st":0,"bm":0},{"ddd":0,"ind":3,"ty":4,"nm":"Group 825","parent":1,"sr":1,"ks":{"o":{"a":0,"k":100,"ix":11},"r":{"a":0,"k":0,"ix":10},"p":{"a":1,"k":[{"i":{"x":0.667,"y":1},"o":{"x":0.333,"y":0},"t":0,"s":[156.703,-108.727,0],"to":[0,0,0],"ti":[0,0,0]},{"i":{"x":0.667,"y":1},"o":{"x":0.333,"y":0},"t":59,"s":[156.703,-117.727,0],"to":[0,0,0],"ti":[0,0,0]},{"t":120,"s":[156.703,-108.727,0]}],"ix":2,"l":2},"a":{"a":0,"k":[0,0,0],"ix":1,"l":2},"s":{"a":0,"k":[100,100,100],"ix":6,"l":2}},"ao":0,"shapes":[{"ty":"rc","d":1,"s":{"a":0,"k":[52.543,52.546],"ix":2},"p":{"a":0,"k":[0,0],"ix":3},"r":{"a":0,"k":0,"ix":4},"nm":"Rectangle Path 1","mn":"ADBE Vector Shape - Rect","hd":false}],"ip":0,"op":3600,"st":0,"bm":0},{"ddd":0,"ind":4,"ty":4,"nm":"Path 2706","parent":3,"sr":1,"ks":{"o":{"a":0,"k":100,"ix":11},"r":{"a":0,"k":0,"ix":10},"p":{"a":0,"k":[-0.021,0.017,0],"ix":2,"l":2},"a":{"a":0,"k":[14.878,14.382,0],"ix":1,"l":2},"s":{"a":0,"k":[100,100,100],"ix":6,"l":2}},"ao":0,"shapes":[{"ty":"gr","it":[{"ind":0,"ty":"sh","ix":1,"ks":{"a":0,"k":{"i":[[0,-7.913],[8.247,0],[0,7.913],[-8.246,0]],"o":[[0,7.913],[-8.246,0],[0,-7.913],[8.247,0]],"v":[[29.755,14.382],[14.877,28.764],[0,14.382],[14.877,0]],"c":true},"ix":2},"nm":"Path 1","mn":"ADBE Vector Shape - Group","hd":false},{"ty":"st","c":{"a":0,"k":[0.694117647059,0.396078431373,0.290196078431,1],"ix":3},"o":{"a":0,"k":100,"ix":4},"w":{"a":0,"k":2,"ix":5},"lc":1,"lj":1,"ml":4,"bm":0,"nm":"Stroke 1","mn":"ADBE Vector Graphic - Stroke","hd":false},{"ty":"fl","c":{"a":0,"k":[1,1,1,1],"ix":4},"o":{"a":0,"k":100,"ix":5},"r":1,"bm":0,"nm":"Fill 1","mn":"ADBE Vector Graphic - Fill","hd":false},{"ty":"tr","p":{"a":0,"k":[0,0],"ix":2},"a":{"a":0,"k":[0,0],"ix":1},"s":{"a":0,"k":[100,100],"ix":3},"r":{"a":0,"k":0,"ix":6},"o":{"a":0,"k":100,"ix":7},"sk":{"a":0,"k":0,"ix":4},"sa":{"a":0,"k":0,"ix":5},"nm":"Transform"}],"nm":"Path 2706","np":3,"cix":2,"bm":0,"ix":1,"mn":"ADBE Vector Group","hd":false}],"ip":0,"op":3600,"st":0,"bm":0},{"ddd":0,"ind":5,"ty":4,"nm":"Path 2705","parent":3,"sr":1,"ks":{"o":{"a":0,"k":100,"ix":11},"r":{"a":0,"k":0,"ix":10},"p":{"a":0,"k":[0,0,0],"ix":2,"l":2},"a":{"a":0,"k":[26.271,26.273,0],"ix":1,"l":2},"s":{"a":0,"k":[100,100,100],"ix":6,"l":2}},"ao":0,"shapes":[{"ty":"gr","it":[{"ind":0,"ty":"sh","ix":1,"ks":{"a":0,"k":{"i":[[0,-14.51],[14.509,0],[0,14.51],[-14.51,0]],"o":[[0,14.51],[-14.51,0],[0,-14.51],[14.509,0]],"v":[[52.543,26.273],[26.272,52.546],[0,26.273],[26.272,0]],"c":true},"ix":2},"nm":"Path 1","mn":"ADBE Vector Shape - Group","hd":false},{"ty":"st","c":{"a":0,"k":[0.694117647059,0.396078431373,0.290196078431,1],"ix":3},"o":{"a":0,"k":100,"ix":4},"w":{"a":0,"k":2,"ix":5},"lc":1,"lj":1,"ml":4,"bm":0,"nm":"Stroke 1","mn":"ADBE Vector Graphic - Stroke","hd":false},{"ty":"gf","o":{"a":0,"k":100,"ix":10},"r":1,"bm":0,"g":{"p":3,"k":{"a":0,"k":[0,1,0.533,0.376,0.5,1,0.741,0.441,1,1,0.949,0.506],"ix":9}},"s":{"a":0,"k":[52,41],"ix":5},"e":{"a":0,"k":[-35,-18],"ix":6},"t":1,"nm":"Gradient Fill 1","mn":"ADBE Vector Graphic - G-Fill","hd":false},{"ty":"tr","p":{"a":0,"k":[0,0],"ix":2},"a":{"a":0,"k":[0,0],"ix":1},"s":{"a":0,"k":[100,100],"ix":3},"r":{"a":0,"k":0,"ix":6},"o":{"a":0,"k":100,"ix":7},"sk":{"a":0,"k":0,"ix":4},"sa":{"a":0,"k":0,"ix":5},"nm":"Transform"}],"nm":"Path 2705","np":3,"cix":2,"bm":0,"ix":1,"mn":"ADBE Vector Group","hd":false}],"ip":0,"op":3600,"st":0,"bm":0},{"ddd":0,"ind":6,"ty":4,"nm":"Rectangle 1147","parent":1,"sr":1,"ks":{"o":{"a":0,"k":100,"ix":11},"r":{"a":0,"k":0,"ix":10},"p":{"a":0,"k":[63.47,141.943,0],"ix":2,"l":2},"a":{"a":0,"k":[0,0,0],"ix":1,"l":2},"s":{"a":0,"k":[100,100,100],"ix":6,"l":2}},"ao":0,"shapes":[{"ty":"gr","it":[{"ty":"rc","d":1,"s":{"a":0,"k":[107.086,14.116],"ix":2},"p":{"a":0,"k":[0,0],"ix":3},"r":{"a":0,"k":7.058,"ix":4},"nm":"Rectangle Path 1","mn":"ADBE Vector Shape - Rect","hd":false},{"ty":"st","c":{"a":0,"k":[0.694117647059,0.396078431373,0.290196078431,1],"ix":3},"o":{"a":0,"k":100,"ix":4},"w":{"a":0,"k":2,"ix":5},"lc":1,"lj":1,"ml":4,"bm":0,"nm":"Stroke 1","mn":"ADBE Vector Graphic - Stroke","hd":false},{"ty":"fl","c":{"a":0,"k":[0.996078431373,0.533333333333,0.376470588235,1],"ix":4},"o":{"a":0,"k":100,"ix":5},"r":1,"bm":0,"nm":"Fill 1","mn":"ADBE Vector Graphic - Fill","hd":false},{"ty":"tr","p":{"a":0,"k":[0,0],"ix":2},"a":{"a":0,"k":[0,0],"ix":1},"s":{"a":0,"k":[100,100],"ix":3},"r":{"a":0,"k":0,"ix":6},"o":{"a":0,"k":100,"ix":7},"sk":{"a":0,"k":0,"ix":4},"sa":{"a":0,"k":0,"ix":5},"nm":"Transform"}],"nm":"Rectangle 1147","np":3,"cix":2,"bm":0,"ix":1,"mn":"ADBE Vector Group","hd":false}],"ip":0,"op":3600,"st":0,"bm":0},{"ddd":0,"ind":7,"ty":4,"nm":"Rectangle 1146","parent":1,"sr":1,"ks":{"o":{"a":0,"k":100,"ix":11},"r":{"a":0,"k":0,"ix":10},"p":{"a":0,"k":[-173.917,-55.167,0],"ix":2,"l":2},"a":{"a":0,"k":[0,0,0],"ix":1,"l":2},"s":{"a":0,"k":[100,100,100],"ix":6,"l":2}},"ao":0,"shapes":[{"ty":"gr","it":[{"ty":"rc","d":1,"s":{"a":0,"k":[52.304,15.116],"ix":2},"p":{"a":0,"k":[0,0],"ix":3},"r":{"a":0,"k":7.558,"ix":4},"nm":"Rectangle Path 1","mn":"ADBE Vector Shape - Rect","hd":false},{"ty":"st","c":{"a":0,"k":[0.694117647059,0.396078431373,0.290196078431,1],"ix":3},"o":{"a":0,"k":100,"ix":4},"w":{"a":0,"k":1,"ix":5},"lc":1,"lj":1,"ml":4,"bm":0,"nm":"Stroke 1","mn":"ADBE Vector Graphic - Stroke","hd":false},{"ty":"fl","c":{"a":0,"k":[0.996078431373,0.564705882353,0.38431372549,1],"ix":4},"o":{"a":0,"k":100,"ix":5},"r":1,"bm":0,"nm":"Fill 1","mn":"ADBE Vector Graphic - Fill","hd":false},{"ty":"tr","p":{"a":0,"k":[0,0],"ix":2},"a":{"a":0,"k":[0,0],"ix":1},"s":{"a":0,"k":[100,100],"ix":3},"r":{"a":0,"k":0,"ix":6},"o":{"a":0,"k":100,"ix":7},"sk":{"a":0,"k":0,"ix":4},"sa":{"a":0,"k":0,"ix":5},"nm":"Transform"}],"nm":"Rectangle 1146","np":3,"cix":2,"bm":0,"ix":1,"mn":"ADBE Vector Group","hd":false}],"ip":0,"op":3600,"st":0,"bm":0},{"ddd":0,"ind":8,"ty":4,"nm":"Rectangle 1145","parent":1,"sr":1,"ks":{"o":{"a":0,"k":100,"ix":11},"r":{"a":0,"k":0,"ix":10},"p":{"a":0,"k":[47.975,-114.671,0],"ix":2,"l":2},"a":{"a":0,"k":[0,0,0],"ix":1,"l":2},"s":{"a":0,"k":[100,100,100],"ix":6,"l":2}},"ao":0,"shapes":[{"ty":"gr","it":[{"ty":"rc","d":1,"s":{"a":0,"k":[42.387,15.116],"ix":2},"p":{"a":0,"k":[0,0],"ix":3},"r":{"a":0,"k":7.558,"ix":4},"nm":"Rectangle Path 1","mn":"ADBE Vector Shape - Rect","hd":false},{"ty":"st","c":{"a":0,"k":[0.694117647059,0.396078431373,0.290196078431,1],"ix":3},"o":{"a":0,"k":100,"ix":4},"w":{"a":0,"k":1,"ix":5},"lc":1,"lj":1,"ml":4,"bm":0,"nm":"Stroke 1","mn":"ADBE Vector Graphic - Stroke","hd":false},{"ty":"gf","o":{"a":0,"k":100,"ix":10},"r":1,"bm":0,"g":{"p":3,"k":{"a":0,"k":[0,1,0.533,0.376,0.5,1,0.741,0.441,1,1,0.949,0.506],"ix":9}},"s":{"a":0,"k":[12,-1],"ix":5},"e":{"a":0,"k":[-55,-16],"ix":6},"t":1,"nm":"Gradient Fill 1","mn":"ADBE Vector Graphic - G-Fill","hd":false},{"ty":"tr","p":{"a":0,"k":[0,0],"ix":2},"a":{"a":0,"k":[0,0],"ix":1},"s":{"a":0,"k":[100,100],"ix":3},"r":{"a":0,"k":0,"ix":6},"o":{"a":0,"k":100,"ix":7},"sk":{"a":0,"k":0,"ix":4},"sa":{"a":0,"k":0,"ix":5},"nm":"Transform"}],"nm":"Rectangle 1145","np":3,"cix":2,"bm":0,"ix":1,"mn":"ADBE Vector Group","hd":false}],"ip":0,"op":3600,"st":0,"bm":0},{"ddd":0,"ind":9,"ty":4,"nm":"eye","parent":1,"sr":1,"ks":{"o":{"a":0,"k":100,"ix":11},"r":{"a":0,"k":0,"ix":10},"p":{"a":0,"k":[32.479,-48.966,0],"ix":2,"l":2},"a":{"a":0,"k":[0,0,0],"ix":1,"l":2},"s":{"a":0,"k":[100,100,100],"ix":6,"l":2}},"ao":0,"shapes":[{"ty":"rc","d":1,"s":{"a":0,"k":[98.689,94.975],"ix":2},"p":{"a":0,"k":[0,0],"ix":3},"r":{"a":0,"k":0,"ix":4},"nm":"Rectangle Path 1","mn":"ADBE Vector Shape - Rect","hd":false}],"ip":0,"op":3600,"st":0,"bm":0},{"ddd":0,"ind":10,"ty":4,"nm":"Path 2704","parent":9,"sr":1,"ks":{"o":{"a":0,"k":100,"ix":11},"r":{"a":0,"k":0,"ix":10},"p":{"a":0,"k":[44.006,-12.397,0],"ix":2,"l":2},"a":{"a":0,"k":[5.339,5.339,0],"ix":1,"l":2},"s":{"a":0,"k":[100,100,100],"ix":6,"l":2}},"ao":0,"shapes":[{"ty":"gr","it":[{"ind":0,"ty":"sh","ix":1,"ks":{"a":0,"k":{"i":[[-2.949,0],[0,2.949],[2.948,0],[0,-2.949]],"o":[[2.948,0],[0,-2.949],[-2.949,0],[0,2.949]],"v":[[5.339,10.678],[10.677,5.339],[5.339,0],[0,5.339]],"c":true},"ix":2},"nm":"Path 1","mn":"ADBE Vector Shape - Group","hd":false},{"ty":"st","c":{"a":0,"k":[0.694117647059,0.396078431373,0.290196078431,1],"ix":3},"o":{"a":0,"k":100,"ix":4},"w":{"a":0,"k":2,"ix":5},"lc":1,"lj":1,"ml":4,"bm":0,"nm":"Stroke 1","mn":"ADBE Vector Graphic - Stroke","hd":false},{"ty":"gf","o":{"a":0,"k":100,"ix":10},"r":1,"bm":0,"g":{"p":3,"k":{"a":0,"k":[0,1,0.533,0.376,0.5,1,0.741,0.441,1,1,0.949,0.506],"ix":9}},"s":{"a":0,"k":[0,0],"ix":5},"e":{"a":0,"k":[14,13.75],"ix":6},"t":1,"nm":"Gradient Fill 1","mn":"ADBE Vector Graphic - G-Fill","hd":false},{"ty":"tr","p":{"a":0,"k":[0,0],"ix":2},"a":{"a":0,"k":[0,0],"ix":1},"s":{"a":0,"k":[100,100],"ix":3},"r":{"a":0,"k":0,"ix":6},"o":{"a":0,"k":100,"ix":7},"sk":{"a":0,"k":0,"ix":4},"sa":{"a":0,"k":0,"ix":5},"nm":"Transform"}],"nm":"Path 2704","np":3,"cix":2,"bm":0,"ix":1,"mn":"ADBE Vector Group","hd":false}],"ip":0,"op":3600,"st":0,"bm":0},{"ddd":0,"ind":11,"ty":4,"nm":"Path 2703","parent":9,"sr":1,"ks":{"o":{"a":0,"k":100,"ix":11},"r":{"a":0,"k":0,"ix":10},"p":{"a":0,"k":[34.09,-28.512,0],"ix":2,"l":2},"a":{"a":0,"k":[5.339,5.339,0],"ix":1,"l":2},"s":{"a":0,"k":[100,100,100],"ix":6,"l":2}},"ao":0,"shapes":[{"ty":"gr","it":[{"ind":0,"ty":"sh","ix":1,"ks":{"a":0,"k":{"i":[[-2.948,0],[0,2.949],[2.949,0],[0,-2.949]],"o":[[2.949,0],[0,-2.949],[-2.948,0],[0,2.949]],"v":[[5.338,10.678],[10.677,5.339],[5.338,0],[0,5.339]],"c":true},"ix":2},"nm":"Path 1","mn":"ADBE Vector Shape - Group","hd":false},{"ty":"st","c":{"a":0,"k":[0.694117647059,0.396078431373,0.290196078431,1],"ix":3},"o":{"a":0,"k":100,"ix":4},"w":{"a":0,"k":2,"ix":5},"lc":1,"lj":1,"ml":4,"bm":0,"nm":"Stroke 1","mn":"ADBE Vector Graphic - Stroke","hd":false},{"ty":"gf","o":{"a":0,"k":100,"ix":10},"r":1,"bm":0,"g":{"p":3,"k":{"a":0,"k":[0,1,0.533,0.376,0.5,1,0.741,0.441,1,1,0.949,0.506],"ix":9}},"s":{"a":0,"k":[0,0],"ix":5},"e":{"a":0,"k":[10.75,13.25],"ix":6},"t":1,"nm":"Gradient Fill 1","mn":"ADBE Vector Graphic - G-Fill","hd":false},{"ty":"tr","p":{"a":0,"k":[0,0],"ix":2},"a":{"a":0,"k":[0,0],"ix":1},"s":{"a":0,"k":[100,100],"ix":3},"r":{"a":0,"k":0,"ix":6},"o":{"a":0,"k":100,"ix":7},"sk":{"a":0,"k":0,"ix":4},"sa":{"a":0,"k":0,"ix":5},"nm":"Transform"}],"nm":"Path 2703","np":3,"cix":2,"bm":0,"ix":1,"mn":"ADBE Vector Group","hd":false}],"ip":0,"op":3600,"st":0,"bm":0},{"ddd":0,"ind":12,"ty":4,"nm":"Path 2702","parent":9,"sr":1,"ks":{"o":{"a":0,"k":100,"ix":11},"r":{"a":0,"k":0,"ix":10},"p":{"a":0,"k":[19.215,-39.67,0],"ix":2,"l":2},"a":{"a":0,"k":[5.339,5.339,0],"ix":1,"l":2},"s":{"a":0,"k":[100,100,100],"ix":6,"l":2}},"ao":0,"shapes":[{"ty":"gr","it":[{"ind":0,"ty":"sh","ix":1,"ks":{"a":0,"k":{"i":[[-2.948,0],[0,2.949],[2.949,0],[0,-2.949]],"o":[[2.949,0],[0,-2.949],[-2.948,0],[0,2.949]],"v":[[5.338,10.678],[10.677,5.339],[5.338,0],[0,5.339]],"c":true},"ix":2},"nm":"Path 1","mn":"ADBE Vector Shape - Group","hd":false},{"ty":"st","c":{"a":0,"k":[0.694117647059,0.396078431373,0.290196078431,1],"ix":3},"o":{"a":0,"k":100,"ix":4},"w":{"a":0,"k":2,"ix":5},"lc":1,"lj":1,"ml":4,"bm":0,"nm":"Stroke 1","mn":"ADBE Vector Graphic - Stroke","hd":false},{"ty":"gf","o":{"a":0,"k":100,"ix":10},"r":1,"bm":0,"g":{"p":3,"k":{"a":0,"k":[0,1,0.533,0.376,0.5,1,0.741,0.441,1,1,0.949,0.506],"ix":9}},"s":{"a":0,"k":[0,0],"ix":5},"e":{"a":0,"k":[12.5,14],"ix":6},"t":1,"nm":"Gradient Fill 1","mn":"ADBE Vector Graphic - G-Fill","hd":false},{"ty":"tr","p":{"a":0,"k":[0,0],"ix":2},"a":{"a":0,"k":[0,0],"ix":1},"s":{"a":0,"k":[100,100],"ix":3},"r":{"a":0,"k":0,"ix":6},"o":{"a":0,"k":100,"ix":7},"sk":{"a":0,"k":0,"ix":4},"sa":{"a":0,"k":0,"ix":5},"nm":"Transform"}],"nm":"Path 2702","np":3,"cix":2,"bm":0,"ix":1,"mn":"ADBE Vector Group","hd":false}],"ip":0,"op":3600,"st":0,"bm":0},{"ddd":0,"ind":13,"ty":4,"nm":"Path 2701","parent":9,"sr":1,"ks":{"o":{"a":0,"k":100,"ix":11},"r":{"a":0,"k":0,"ix":10},"p":{"a":0,"k":[44.006,11.156,0],"ix":2,"l":2},"a":{"a":0,"k":[5.339,5.339,0],"ix":1,"l":2},"s":{"a":0,"k":[100,100,100],"ix":6,"l":2}},"ao":0,"shapes":[{"ty":"gr","it":[{"ind":0,"ty":"sh","ix":1,"ks":{"a":0,"k":{"i":[[-2.949,0],[0,2.949],[2.948,0],[0,-2.948]],"o":[[2.948,0],[0,-2.948],[-2.949,0],[0,2.949]],"v":[[5.339,10.677],[10.677,5.338],[5.339,0],[0,5.338]],"c":true},"ix":2},"nm":"Path 1","mn":"ADBE Vector Shape - Group","hd":false},{"ty":"st","c":{"a":0,"k":[0.694117647059,0.396078431373,0.290196078431,1],"ix":3},"o":{"a":0,"k":100,"ix":4},"w":{"a":0,"k":2,"ix":5},"lc":1,"lj":1,"ml":4,"bm":0,"nm":"Stroke 1","mn":"ADBE Vector Graphic - Stroke","hd":false},{"ty":"gf","o":{"a":0,"k":100,"ix":10},"r":1,"bm":0,"g":{"p":3,"k":{"a":0,"k":[0,1,0.533,0.376,0.5,1,0.741,0.441,1,1,0.949,0.506],"ix":9}},"s":{"a":0,"k":[0,0],"ix":5},"e":{"a":0,"k":[9.75,14],"ix":6},"t":1,"nm":"Gradient Fill 1","mn":"ADBE Vector Graphic - G-Fill","hd":false},{"ty":"tr","p":{"a":0,"k":[0,0],"ix":2},"a":{"a":0,"k":[0,0],"ix":1},"s":{"a":0,"k":[100,100],"ix":3},"r":{"a":0,"k":0,"ix":6},"o":{"a":0,"k":100,"ix":7},"sk":{"a":0,"k":0,"ix":4},"sa":{"a":0,"k":0,"ix":5},"nm":"Transform"}],"nm":"Path 2701","np":3,"cix":2,"bm":0,"ix":1,"mn":"ADBE Vector Group","hd":false}],"ip":0,"op":3600,"st":0,"bm":0},{"ddd":0,"ind":14,"ty":4,"nm":"Path 2700","parent":9,"sr":1,"ks":{"o":{"a":0,"k":100,"ix":11},"r":{"a":0,"k":0,"ix":10},"p":{"a":0,"k":[34.258,27.504,0],"ix":2,"l":2},"a":{"a":0,"k":[5.339,5.339,0],"ix":1,"l":2},"s":{"a":0,"k":[100,100,100],"ix":6,"l":2}},"ao":0,"shapes":[{"ty":"gr","it":[{"ind":0,"ty":"sh","ix":1,"ks":{"a":0,"k":{"i":[[-2.948,0],[0,2.949],[2.949,0],[0,-2.948]],"o":[[2.949,0],[0,-2.948],[-2.948,0],[0,2.949]],"v":[[5.338,10.678],[10.677,5.339],[5.338,0],[0,5.339]],"c":true},"ix":2},"nm":"Path 1","mn":"ADBE Vector Shape - Group","hd":false},{"ty":"st","c":{"a":0,"k":[0.694117647059,0.396078431373,0.290196078431,1],"ix":3},"o":{"a":0,"k":100,"ix":4},"w":{"a":0,"k":2,"ix":5},"lc":1,"lj":1,"ml":4,"bm":0,"nm":"Stroke 1","mn":"ADBE Vector Graphic - Stroke","hd":false},{"ty":"gf","o":{"a":0,"k":100,"ix":10},"r":1,"bm":0,"g":{"p":3,"k":{"a":0,"k":[0,1,0.533,0.376,0.5,1,0.741,0.441,1,1,0.949,0.506],"ix":9}},"s":{"a":0,"k":[0,0],"ix":5},"e":{"a":0,"k":[9.5,15],"ix":6},"t":1,"nm":"Gradient Fill 1","mn":"ADBE Vector Graphic - G-Fill","hd":false},{"ty":"tr","p":{"a":0,"k":[0,0],"ix":2},"a":{"a":0,"k":[0,0],"ix":1},"s":{"a":0,"k":[100,100],"ix":3},"r":{"a":0,"k":0,"ix":6},"o":{"a":0,"k":100,"ix":7},"sk":{"a":0,"k":0,"ix":4},"sa":{"a":0,"k":0,"ix":5},"nm":"Transform"}],"nm":"Path 2700","np":3,"cix":2,"bm":0,"ix":1,"mn":"ADBE Vector Group","hd":false}],"ip":0,"op":3600,"st":0,"bm":0},{"ddd":0,"ind":15,"ty":4,"nm":"Path 2699","parent":9,"sr":1,"ks":{"o":{"a":0,"k":100,"ix":11},"r":{"a":0,"k":0,"ix":10},"p":{"a":0,"k":[19.215,37.191,0],"ix":2,"l":2},"a":{"a":0,"k":[5.339,5.339,0],"ix":1,"l":2},"s":{"a":0,"k":[100,100,100],"ix":6,"l":2}},"ao":0,"shapes":[{"ty":"gr","it":[{"ind":0,"ty":"sh","ix":1,"ks":{"a":0,"k":{"i":[[-2.948,0],[0,2.948],[2.949,0],[0,-2.949]],"o":[[2.949,0],[0,-2.949],[-2.948,0],[0,2.948]],"v":[[5.338,10.677],[10.677,5.339],[5.338,0],[0,5.339]],"c":true},"ix":2},"nm":"Path 1","mn":"ADBE Vector Shape - Group","hd":false},{"ty":"st","c":{"a":0,"k":[0.694117647059,0.396078431373,0.290196078431,1],"ix":3},"o":{"a":0,"k":100,"ix":4},"w":{"a":0,"k":2,"ix":5},"lc":1,"lj":1,"ml":4,"bm":0,"nm":"Stroke 1","mn":"ADBE Vector Graphic - Stroke","hd":false},{"ty":"gf","o":{"a":0,"k":100,"ix":10},"r":1,"bm":0,"g":{"p":3,"k":{"a":0,"k":[0,1,0.533,0.376,0.5,1,0.741,0.441,1,1,0.949,0.506],"ix":9}},"s":{"a":0,"k":[0,0],"ix":5},"e":{"a":0,"k":[11.25,14.5],"ix":6},"t":1,"nm":"Gradient Fill 1","mn":"ADBE Vector Graphic - G-Fill","hd":false},{"ty":"tr","p":{"a":0,"k":[0,0],"ix":2},"a":{"a":0,"k":[0,0],"ix":1},"s":{"a":0,"k":[100,100],"ix":3},"r":{"a":0,"k":0,"ix":6},"o":{"a":0,"k":100,"ix":7},"sk":{"a":0,"k":0,"ix":4},"sa":{"a":0,"k":0,"ix":5},"nm":"Transform"}],"nm":"Path 2699","np":3,"cix":2,"bm":0,"ix":1,"mn":"ADBE Vector Group","hd":false}],"ip":0,"op":3600,"st":0,"bm":0},{"ddd":0,"ind":16,"ty":4,"nm":"Path 2698","parent":9,"sr":1,"ks":{"o":{"a":0,"k":100,"ix":11},"r":{"a":0,"k":0,"ix":10},"p":{"a":0,"k":[0.621,42.148,0],"ix":2,"l":2},"a":{"a":0,"k":[5.339,5.339,0],"ix":1,"l":2},"s":{"a":0,"k":[100,100,100],"ix":6,"l":2}},"ao":0,"shapes":[{"ty":"gr","it":[{"ind":0,"ty":"sh","ix":1,"ks":{"a":0,"k":{"i":[[-2.949,0],[0,2.948],[2.948,0],[0,-2.949]],"o":[[2.948,0],[0,-2.949],[-2.949,0],[0,2.948]],"v":[[5.339,10.677],[10.677,5.339],[5.339,0],[0,5.339]],"c":true},"ix":2},"nm":"Path 1","mn":"ADBE Vector Shape - Group","hd":false},{"ty":"st","c":{"a":0,"k":[0.694117647059,0.396078431373,0.290196078431,1],"ix":3},"o":{"a":0,"k":100,"ix":4},"w":{"a":0,"k":2,"ix":5},"lc":1,"lj":1,"ml":4,"bm":0,"nm":"Stroke 1","mn":"ADBE Vector Graphic - Stroke","hd":false},{"ty":"gf","o":{"a":0,"k":100,"ix":10},"r":1,"bm":0,"g":{"p":3,"k":{"a":0,"k":[0,1,0.533,0.376,0.5,1,0.741,0.441,1,1,0.949,0.506],"ix":9}},"s":{"a":0,"k":[0,0],"ix":5},"e":{"a":0,"k":[13.75,9.5],"ix":6},"t":1,"nm":"Gradient Fill 1","mn":"ADBE Vector Graphic - G-Fill","hd":false},{"ty":"tr","p":{"a":0,"k":[0,0],"ix":2},"a":{"a":0,"k":[0,0],"ix":1},"s":{"a":0,"k":[100,100],"ix":3},"r":{"a":0,"k":0,"ix":6},"o":{"a":0,"k":100,"ix":7},"sk":{"a":0,"k":0,"ix":4},"sa":{"a":0,"k":0,"ix":5},"nm":"Transform"}],"nm":"Path 2698","np":3,"cix":2,"bm":0,"ix":1,"mn":"ADBE Vector Group","hd":false}],"ip":0,"op":3600,"st":0,"bm":0},{"ddd":0,"ind":17,"ty":4,"nm":"Path 2697","parent":9,"sr":1,"ks":{"o":{"a":0,"k":100,"ix":11},"r":{"a":0,"k":0,"ix":10},"p":{"a":0,"k":[-19.213,37.191,0],"ix":2,"l":2},"a":{"a":0,"k":[5.339,5.339,0],"ix":1,"l":2},"s":{"a":0,"k":[100,100,100],"ix":6,"l":2}},"ao":0,"shapes":[{"ty":"gr","it":[{"ind":0,"ty":"sh","ix":1,"ks":{"a":0,"k":{"i":[[-2.949,0],[0,2.948],[2.948,0],[0,-2.949]],"o":[[2.948,0],[0,-2.949],[-2.949,0],[0,2.948]],"v":[[5.339,10.677],[10.677,5.339],[5.339,0],[0,5.339]],"c":true},"ix":2},"nm":"Path 1","mn":"ADBE Vector Shape - Group","hd":false},{"ty":"st","c":{"a":0,"k":[0.694117647059,0.396078431373,0.290196078431,1],"ix":3},"o":{"a":0,"k":100,"ix":4},"w":{"a":0,"k":2,"ix":5},"lc":1,"lj":1,"ml":4,"bm":0,"nm":"Stroke 1","mn":"ADBE Vector Graphic - Stroke","hd":false},{"ty":"gf","o":{"a":0,"k":100,"ix":10},"r":1,"bm":0,"g":{"p":3,"k":{"a":0,"k":[0,1,0.533,0.376,0.5,1,0.741,0.441,1,1,0.949,0.506],"ix":9}},"s":{"a":0,"k":[0,0],"ix":5},"e":{"a":0,"k":[14,13.5],"ix":6},"t":1,"nm":"Gradient Fill 1","mn":"ADBE Vector Graphic - G-Fill","hd":false},{"ty":"tr","p":{"a":0,"k":[0,0],"ix":2},"a":{"a":0,"k":[0,0],"ix":1},"s":{"a":0,"k":[100,100],"ix":3},"r":{"a":0,"k":0,"ix":6},"o":{"a":0,"k":100,"ix":7},"sk":{"a":0,"k":0,"ix":4},"sa":{"a":0,"k":0,"ix":5},"nm":"Transform"}],"nm":"Path 2697","np":3,"cix":2,"bm":0,"ix":1,"mn":"ADBE Vector Group","hd":false}],"ip":0,"op":3600,"st":0,"bm":0},{"ddd":0,"ind":18,"ty":4,"nm":"Path 2696","parent":9,"sr":1,"ks":{"o":{"a":0,"k":100,"ix":11},"r":{"a":0,"k":0,"ix":10},"p":{"a":0,"k":[-34.09,27.272,0],"ix":2,"l":2},"a":{"a":0,"k":[5.339,5.339,0],"ix":1,"l":2},"s":{"a":0,"k":[100,100,100],"ix":6,"l":2}},"ao":0,"shapes":[{"ty":"gr","it":[{"ind":0,"ty":"sh","ix":1,"ks":{"a":0,"k":{"i":[[-2.949,0],[0,2.948],[2.948,0],[0,-2.949]],"o":[[2.948,0],[0,-2.949],[-2.949,0],[0,2.948]],"v":[[5.339,10.678],[10.677,5.339],[5.339,0],[0,5.339]],"c":true},"ix":2},"nm":"Path 1","mn":"ADBE Vector Shape - Group","hd":false},{"ty":"st","c":{"a":0,"k":[0.694117647059,0.396078431373,0.290196078431,1],"ix":3},"o":{"a":0,"k":100,"ix":4},"w":{"a":0,"k":2,"ix":5},"lc":1,"lj":1,"ml":4,"bm":0,"nm":"Stroke 1","mn":"ADBE Vector Graphic - Stroke","hd":false},{"ty":"gf","o":{"a":0,"k":100,"ix":10},"r":1,"bm":0,"g":{"p":3,"k":{"a":0,"k":[0,1,0.533,0.376,0.5,1,0.741,0.441,1,1,0.949,0.506],"ix":9}},"s":{"a":0,"k":[0,0],"ix":5},"e":{"a":0,"k":[6.25,18.25],"ix":6},"t":1,"nm":"Gradient Fill 1","mn":"ADBE Vector Graphic - G-Fill","hd":false},{"ty":"tr","p":{"a":0,"k":[0,0],"ix":2},"a":{"a":0,"k":[0,0],"ix":1},"s":{"a":0,"k":[100,100],"ix":3},"r":{"a":0,"k":0,"ix":6},"o":{"a":0,"k":100,"ix":7},"sk":{"a":0,"k":0,"ix":4},"sa":{"a":0,"k":0,"ix":5},"nm":"Transform"}],"nm":"Path 2696","np":3,"cix":2,"bm":0,"ix":1,"mn":"ADBE Vector Group","hd":false}],"ip":0,"op":3600,"st":0,"bm":0},{"ddd":0,"ind":19,"ty":4,"nm":"Path 2695","parent":9,"sr":1,"ks":{"o":{"a":0,"k":100,"ix":11},"r":{"a":0,"k":0,"ix":10},"p":{"a":0,"k":[-44.006,11.156,0],"ix":2,"l":2},"a":{"a":0,"k":[5.339,5.339,0],"ix":1,"l":2},"s":{"a":0,"k":[100,100,100],"ix":6,"l":2}},"ao":0,"shapes":[{"ty":"gr","it":[{"ind":0,"ty":"sh","ix":1,"ks":{"a":0,"k":{"i":[[-2.949,0],[0,2.949],[2.948,0],[0,-2.948]],"o":[[2.948,0],[0,-2.948],[-2.949,0],[0,2.949]],"v":[[5.339,10.677],[10.677,5.338],[5.339,0],[0,5.338]],"c":true},"ix":2},"nm":"Path 1","mn":"ADBE Vector Shape - Group","hd":false},{"ty":"st","c":{"a":0,"k":[0.694117647059,0.396078431373,0.290196078431,1],"ix":3},"o":{"a":0,"k":100,"ix":4},"w":{"a":0,"k":2,"ix":5},"lc":1,"lj":1,"ml":4,"bm":0,"nm":"Stroke 1","mn":"ADBE Vector Graphic - Stroke","hd":false},{"ty":"gf","o":{"a":0,"k":100,"ix":10},"r":1,"bm":0,"g":{"p":3,"k":{"a":0,"k":[0,1,0.533,0.376,0.5,1,0.741,0.441,1,1,0.949,0.506],"ix":9}},"s":{"a":0,"k":[0,0],"ix":5},"e":{"a":0,"k":[9,13],"ix":6},"t":1,"nm":"Gradient Fill 1","mn":"ADBE Vector Graphic - G-Fill","hd":false},{"ty":"tr","p":{"a":0,"k":[0,0],"ix":2},"a":{"a":0,"k":[0,0],"ix":1},"s":{"a":0,"k":[100,100],"ix":3},"r":{"a":0,"k":0,"ix":6},"o":{"a":0,"k":100,"ix":7},"sk":{"a":0,"k":0,"ix":4},"sa":{"a":0,"k":0,"ix":5},"nm":"Transform"}],"nm":"Path 2695","np":3,"cix":2,"bm":0,"ix":1,"mn":"ADBE Vector Group","hd":false}],"ip":0,"op":3600,"st":0,"bm":0},{"ddd":0,"ind":20,"ty":4,"nm":"Path 2694","parent":9,"sr":1,"ks":{"o":{"a":0,"k":100,"ix":11},"r":{"a":0,"k":0,"ix":10},"p":{"a":0,"k":[-44.006,-12.397,0],"ix":2,"l":2},"a":{"a":0,"k":[5.339,5.339,0],"ix":1,"l":2},"s":{"a":0,"k":[100,100,100],"ix":6,"l":2}},"ao":0,"shapes":[{"ty":"gr","it":[{"ind":0,"ty":"sh","ix":1,"ks":{"a":0,"k":{"i":[[-2.949,0],[0,2.949],[2.948,0],[0,-2.949]],"o":[[2.948,0],[0,-2.949],[-2.949,0],[0,2.949]],"v":[[5.339,10.678],[10.677,5.339],[5.339,0],[0,5.339]],"c":true},"ix":2},"nm":"Path 1","mn":"ADBE Vector Shape - Group","hd":false},{"ty":"st","c":{"a":0,"k":[0.694117647059,0.396078431373,0.290196078431,1],"ix":3},"o":{"a":0,"k":100,"ix":4},"w":{"a":0,"k":2,"ix":5},"lc":1,"lj":1,"ml":4,"bm":0,"nm":"Stroke 1","mn":"ADBE Vector Graphic - Stroke","hd":false},{"ty":"gf","o":{"a":0,"k":100,"ix":10},"r":1,"bm":0,"g":{"p":3,"k":{"a":0,"k":[0,1,0.533,0.376,0.5,1,0.741,0.441,1,1,0.949,0.506],"ix":9}},"s":{"a":0,"k":[9.75,5.5],"ix":5},"e":{"a":0,"k":[-4.75,4.25],"ix":6},"t":1,"nm":"Gradient Fill 1","mn":"ADBE Vector Graphic - G-Fill","hd":false},{"ty":"tr","p":{"a":0,"k":[0,0],"ix":2},"a":{"a":0,"k":[0,0],"ix":1},"s":{"a":0,"k":[100,100],"ix":3},"r":{"a":0,"k":0,"ix":6},"o":{"a":0,"k":100,"ix":7},"sk":{"a":0,"k":0,"ix":4},"sa":{"a":0,"k":0,"ix":5},"nm":"Transform"}],"nm":"Path 2694","np":3,"cix":2,"bm":0,"ix":1,"mn":"ADBE Vector Group","hd":false}],"ip":0,"op":3600,"st":0,"bm":0},{"ddd":0,"ind":21,"ty":4,"nm":"Path 2693","parent":9,"sr":1,"ks":{"o":{"a":0,"k":100,"ix":11},"r":{"a":0,"k":0,"ix":10},"p":{"a":0,"k":[-34.09,-29.752,0],"ix":2,"l":2},"a":{"a":0,"k":[5.339,5.339,0],"ix":1,"l":2},"s":{"a":0,"k":[100,100,100],"ix":6,"l":2}},"ao":0,"shapes":[{"ty":"gr","it":[{"ind":0,"ty":"sh","ix":1,"ks":{"a":0,"k":{"i":[[-2.949,0],[0,2.949],[2.948,0],[0,-2.949]],"o":[[2.948,0],[0,-2.949],[-2.949,0],[0,2.949]],"v":[[5.339,10.678],[10.677,5.339],[5.339,0],[0,5.339]],"c":true},"ix":2},"nm":"Path 1","mn":"ADBE Vector Shape - Group","hd":false},{"ty":"st","c":{"a":0,"k":[0.694117647059,0.396078431373,0.290196078431,1],"ix":3},"o":{"a":0,"k":100,"ix":4},"w":{"a":0,"k":2,"ix":5},"lc":1,"lj":1,"ml":4,"bm":0,"nm":"Stroke 1","mn":"ADBE Vector Graphic - Stroke","hd":false},{"ty":"gf","o":{"a":0,"k":100,"ix":10},"r":1,"bm":0,"g":{"p":3,"k":{"a":0,"k":[0,1,0.533,0.376,0.5,1,0.741,0.441,1,1,0.949,0.506],"ix":9}},"s":{"a":0,"k":[0,0],"ix":5},"e":{"a":0,"k":[9,15.5],"ix":6},"t":1,"nm":"Gradient Fill 1","mn":"ADBE Vector Graphic - G-Fill","hd":false},{"ty":"tr","p":{"a":0,"k":[0,0],"ix":2},"a":{"a":0,"k":[0,0],"ix":1},"s":{"a":0,"k":[100,100],"ix":3},"r":{"a":0,"k":0,"ix":6},"o":{"a":0,"k":100,"ix":7},"sk":{"a":0,"k":0,"ix":4},"sa":{"a":0,"k":0,"ix":5},"nm":"Transform"}],"nm":"Path 2693","np":3,"cix":2,"bm":0,"ix":1,"mn":"ADBE Vector Group","hd":false}],"ip":0,"op":3600,"st":0,"bm":0},{"ddd":0,"ind":22,"ty":4,"nm":"Path 2692","parent":9,"sr":1,"ks":{"o":{"a":0,"k":100,"ix":11},"r":{"a":0,"k":0,"ix":10},"p":{"a":0,"k":[-19.213,-39.67,0],"ix":2,"l":2},"a":{"a":0,"k":[5.339,5.339,0],"ix":1,"l":2},"s":{"a":0,"k":[100,100,100],"ix":6,"l":2}},"ao":0,"shapes":[{"ty":"gr","it":[{"ind":0,"ty":"sh","ix":1,"ks":{"a":0,"k":{"i":[[-2.949,0],[0,2.949],[2.948,0],[0,-2.949]],"o":[[2.948,0],[0,-2.949],[-2.949,0],[0,2.949]],"v":[[5.339,10.678],[10.677,5.339],[5.339,0],[0,5.339]],"c":true},"ix":2},"nm":"Path 1","mn":"ADBE Vector Shape - Group","hd":false},{"ty":"st","c":{"a":0,"k":[0.694117647059,0.396078431373,0.290196078431,1],"ix":3},"o":{"a":0,"k":100,"ix":4},"w":{"a":0,"k":2,"ix":5},"lc":1,"lj":1,"ml":4,"bm":0,"nm":"Stroke 1","mn":"ADBE Vector Graphic - Stroke","hd":false},{"ty":"gf","o":{"a":0,"k":100,"ix":10},"r":1,"bm":0,"g":{"p":3,"k":{"a":0,"k":[0,1,0.533,0.376,0.5,1,0.741,0.441,1,1,0.949,0.506],"ix":9}},"s":{"a":0,"k":[0,0],"ix":5},"e":{"a":0,"k":[11.5,15],"ix":6},"t":1,"nm":"Gradient Fill 1","mn":"ADBE Vector Graphic - G-Fill","hd":false},{"ty":"tr","p":{"a":0,"k":[0,0],"ix":2},"a":{"a":0,"k":[0,0],"ix":1},"s":{"a":0,"k":[100,100],"ix":3},"r":{"a":0,"k":0,"ix":6},"o":{"a":0,"k":100,"ix":7},"sk":{"a":0,"k":0,"ix":4},"sa":{"a":0,"k":0,"ix":5},"nm":"Transform"}],"nm":"Path 2692","np":3,"cix":2,"bm":0,"ix":1,"mn":"ADBE Vector Group","hd":false}],"ip":0,"op":3600,"st":0,"bm":0},{"ddd":0,"ind":23,"ty":4,"nm":"Path 2691","parent":9,"sr":1,"ks":{"o":{"a":0,"k":100,"ix":11},"r":{"a":0,"k":0,"ix":10},"p":{"a":0,"k":[0.621,-42.148,0],"ix":2,"l":2},"a":{"a":0,"k":[5.339,5.339,0],"ix":1,"l":2},"s":{"a":0,"k":[100,100,100],"ix":6,"l":2}},"ao":0,"shapes":[{"ty":"gr","it":[{"ind":0,"ty":"sh","ix":1,"ks":{"a":0,"k":{"i":[[-2.949,0],[0,2.949],[2.948,0],[0,-2.949]],"o":[[2.948,0],[0,-2.949],[-2.949,0],[0,2.949]],"v":[[5.339,10.678],[10.677,5.339],[5.339,0],[0,5.339]],"c":true},"ix":2},"nm":"Path 1","mn":"ADBE Vector Shape - Group","hd":false},{"ty":"st","c":{"a":0,"k":[0.694117647059,0.396078431373,0.290196078431,1],"ix":3},"o":{"a":0,"k":100,"ix":4},"w":{"a":0,"k":2,"ix":5},"lc":1,"lj":1,"ml":4,"bm":0,"nm":"Stroke 1","mn":"ADBE Vector Graphic - Stroke","hd":false},{"ty":"gf","o":{"a":0,"k":100,"ix":10},"r":1,"bm":0,"g":{"p":3,"k":{"a":0,"k":[0,1,0.533,0.376,0.5,1,0.741,0.441,1,1,0.949,0.506],"ix":9}},"s":{"a":0,"k":[0,0],"ix":5},"e":{"a":0,"k":[15.5,13.5],"ix":6},"t":1,"nm":"Gradient Fill 1","mn":"ADBE Vector Graphic - G-Fill","hd":false},{"ty":"tr","p":{"a":0,"k":[0,0],"ix":2},"a":{"a":0,"k":[0,0],"ix":1},"s":{"a":0,"k":[100,100],"ix":3},"r":{"a":0,"k":0,"ix":6},"o":{"a":0,"k":100,"ix":7},"sk":{"a":0,"k":0,"ix":4},"sa":{"a":0,"k":0,"ix":5},"nm":"Transform"}],"nm":"Path 2691","np":3,"cix":2,"bm":0,"ix":1,"mn":"ADBE Vector Group","hd":false}],"ip":0,"op":3600,"st":0,"bm":0},{"ddd":0,"ind":24,"ty":4,"nm":"Path 2690","parent":9,"sr":1,"ks":{"o":{"a":0,"k":100,"ix":11},"r":{"a":0,"k":0,"ix":10},"p":{"a":0,"k":[0.31,-0.93,0],"ix":2,"l":2},"a":{"a":0,"k":[39.358,38.12,0],"ix":1,"l":2},"s":{"a":0,"k":[100,100,100],"ix":6,"l":2}},"ao":0,"shapes":[{"ty":"gr","it":[{"ind":0,"ty":"sh","ix":1,"ks":{"a":0,"k":{"i":[[0,0],[0,0]],"o":[[0,0],[0,0]],"v":[[39.668,16.116],[39.668,0]],"c":false},"ix":2},"nm":"Path 1","mn":"ADBE Vector Shape - Group","hd":false},{"ind":1,"ty":"sh","ix":2,"ks":{"a":0,"k":{"i":[[0,0],[0,0],[-1.54,0],[0,0],[0,1.54],[0,0]],"o":[[0,0],[0,-1.54],[0,0],[1.54,0],[0,0],[0,0]],"v":[[52.064,18.595],[52.064,13.326],[54.853,10.537],[54.853,10.537],[57.642,7.748],[57.642,4.339]],"c":false},"ix":2},"nm":"Path 2","mn":"ADBE Vector Shape - Group","hd":false},{"ind":2,"ty":"sh","ix":3,"ks":{"a":0,"k":{"i":[[0,0],[0,0],[-2.567,0],[0,0],[0,2.054],[0,0]],"o":[[0,0],[0,-2.567],[0,0],[2.054,0],[0,0],[0,0]],"v":[[63.22,25.413],[63.22,23.244],[67.869,18.595],[68.799,18.595],[72.518,14.876],[72.518,14.876]],"c":false},"ix":2},"nm":"Path 3","mn":"ADBE Vector Shape - Group","hd":false},{"ind":3,"ty":"sh","ix":4,"ks":{"a":0,"k":{"i":[[0,0],[0,0],[-3.765,0],[0,0]],"o":[[0,0],[0,-3.766],[0,0],[0,0]],"v":[[71.278,34.091],[71.278,34.091],[78.096,27.273],[78.716,27.273]],"c":false},"ix":2},"nm":"Path 4","mn":"ADBE Vector Shape - Group","hd":false},{"ind":4,"ty":"sh","ix":5,"ks":{"a":0,"k":{"i":[[0,0],[0,0],[-3.423,0],[0,0]],"o":[[0,0],[0,3.423],[0,0],[0,0]],"v":[[71.278,42.149],[71.278,43.389],[77.476,49.587],[77.476,49.587]],"c":false},"ix":2},"nm":"Path 5","mn":"ADBE Vector Shape - Group","hd":false},{"ind":5,"ty":"sh","ix":6,"ks":{"a":0,"k":{"i":[[0,0],[0,0],[-2.567,0],[0,0],[0,-1.711],[0,0]],"o":[[0,0],[0,2.568],[0,0],[1.712,0],[0,0],[0,0]],"v":[[63.22,49.587],[63.22,53.616],[67.869,58.265],[69.418,58.265],[72.518,61.364],[72.518,61.364]],"c":false},"ix":2},"nm":"Path 6","mn":"ADBE Vector Shape - Group","hd":false},{"ind":6,"ty":"sh","ix":7,"ks":{"a":0,"k":{"i":[[0,0],[0,0],[-1.54,0],[0,0],[0,-1.54],[0,0]],"o":[[0,0],[0,1.54],[0,0],[1.54,0],[0,0],[0,0]],"v":[[52.064,57.025],[52.064,63.534],[54.853,66.323],[54.853,66.323],[57.642,69.112],[57.642,71.901]],"c":false},"ix":2},"nm":"Path 7","mn":"ADBE Vector Shape - Group","hd":false},{"ind":7,"ty":"sh","ix":8,"ks":{"a":0,"k":{"i":[[0,0],[0,0]],"o":[[0,0],[0,0]],"v":[[39.048,60.124],[39.048,76.24]],"c":false},"ix":2},"nm":"Path 8","mn":"ADBE Vector Shape - Group","hd":false},{"ind":8,"ty":"sh","ix":9,"ks":{"a":0,"k":{"i":[[0,0],[0,0],[1.883,0],[0,0],[0,-1.883],[0,0]],"o":[[0,0],[0,1.883],[0,0],[-1.883,0],[0,0],[0,0]],"v":[[26.652,57.025],[26.652,62.914],[23.243,66.323],[23.243,66.323],[19.834,69.732],[19.834,71.901]],"c":false},"ix":2},"nm":"Path 9","mn":"ADBE Vector Shape - Group","hd":false},{"ind":9,"ty":"sh","ix":10,"ks":{"a":0,"k":{"i":[[0,0],[0,0],[2.738,0],[0,0],[0,-2.054],[0,0]],"o":[[0,0],[0,2.739],[0,0],[-2.053,0],[0,0],[0,0]],"v":[[14.875,49.587],[14.875,53.306],[9.917,58.265],[8.677,58.265],[4.958,61.984],[4.958,61.984]],"c":false},"ix":2},"nm":"Path 10","mn":"ADBE Vector Shape - Group","hd":false},{"ind":10,"ty":"sh","ix":11,"ks":{"a":0,"k":{"i":[[0,0],[0,0],[0,3.423],[0,0]],"o":[[0,0],[3.423,0],[0,0],[0,0]],"v":[[0,49.587],[0,49.587],[6.198,43.389],[6.198,42.149]],"c":false},"ix":2},"nm":"Path 11","mn":"ADBE Vector Shape - Group","hd":false},{"ind":11,"ty":"sh","ix":12,"ks":{"a":0,"k":{"i":[[0,0],[0,0],[3.423,0],[0,0]],"o":[[0,0],[0,-3.423],[0,0],[0,0]],"v":[[6.198,34.091],[6.198,31.611],[0,25.413],[0,25.413]],"c":false},"ix":2},"nm":"Path 12","mn":"ADBE Vector Shape - Group","hd":false},{"ind":12,"ty":"sh","ix":13,"ks":{"a":0,"k":{"i":[[0,0],[0,0],[-2.739,0],[0,0],[0,-2.739],[0,0]],"o":[[0,0],[0,2.739],[0,0],[2.738,0],[0,0],[0,0]],"v":[[4.958,13.636],[4.958,13.636],[9.917,18.595],[9.917,18.595],[14.875,23.553],[14.875,25.413]],"c":false},"ix":2},"nm":"Path 13","mn":"ADBE Vector Shape - Group","hd":false},{"ind":13,"ty":"sh","ix":14,"ks":{"a":0,"k":{"i":[[0,0],[0,0],[1.883,0],[0,0],[0,1.883],[0,0]],"o":[[0,0],[0,-1.883],[0,0],[-1.883,0],[0,0],[0,0]],"v":[[26.652,18.595],[26.652,13.946],[23.243,10.537],[23.243,10.537],[19.834,7.128],[19.834,4.339]],"c":false},"ix":2},"nm":"Path 14","mn":"ADBE Vector Shape - Group","hd":false},{"ty":"st","c":{"a":0,"k":[0.694117647059,0.396078431373,0.290196078431,1],"ix":3},"o":{"a":0,"k":100,"ix":4},"w":{"a":0,"k":2,"ix":5},"lc":1,"lj":1,"ml":4,"bm":0,"nm":"Stroke 1","mn":"ADBE Vector Graphic - Stroke","hd":false},{"ty":"tr","p":{"a":0,"k":[0,0],"ix":2},"a":{"a":0,"k":[0,0],"ix":1},"s":{"a":0,"k":[100,100],"ix":3},"r":{"a":0,"k":0,"ix":6},"o":{"a":0,"k":100,"ix":7},"sk":{"a":0,"k":0,"ix":4},"sa":{"a":0,"k":0,"ix":5},"nm":"Transform"}],"nm":"Path 2690","np":16,"cix":2,"bm":0,"ix":1,"mn":"ADBE Vector Group","hd":false}],"ip":0,"op":3600,"st":0,"bm":0},{"ddd":0,"ind":25,"ty":4,"nm":"Path 2689","parent":9,"sr":1,"ks":{"o":{"a":0,"k":100,"ix":11},"r":{"a":0,"k":0,"ix":10},"p":{"a":0,"k":[3.142,-3.852,0],"ix":2,"l":2},"a":{"a":0,"k":[3.138,2.618,0],"ix":1,"l":2},"s":{"a":0,"k":[100,100,100],"ix":6,"l":2}},"ao":0,"shapes":[{"ty":"gr","it":[{"ind":0,"ty":"sh","ix":1,"ks":{"a":0,"k":{"i":[[0,0],[0.617,-3.101]],"o":[[3.716,-1.25],[0,0]],"v":[[0,0.284],[6.198,5.235]],"c":false},"ix":2},"nm":"Path 1","mn":"ADBE Vector Shape - Group","hd":false},{"ty":"st","c":{"a":0,"k":[1,1,1,1],"ix":3},"o":{"a":0,"k":100,"ix":4},"w":{"a":0,"k":2,"ix":5},"lc":2,"lj":1,"ml":4,"bm":0,"nm":"Stroke 1","mn":"ADBE Vector Graphic - Stroke","hd":false},{"ty":"tr","p":{"a":0,"k":[0,0],"ix":2},"a":{"a":0,"k":[0,0],"ix":1},"s":{"a":0,"k":[100,100],"ix":3},"r":{"a":0,"k":0,"ix":6},"o":{"a":0,"k":100,"ix":7},"sk":{"a":0,"k":0,"ix":4},"sa":{"a":0,"k":0,"ix":5},"nm":"Transform"}],"nm":"Path 2689","np":3,"cix":2,"bm":0,"ix":1,"mn":"ADBE Vector Group","hd":false}],"ip":0,"op":3600,"st":0,"bm":0},{"ddd":0,"ind":26,"ty":4,"nm":"Ellipse 122","parent":9,"sr":1,"ks":{"o":{"a":0,"k":100,"ix":11},"r":{"a":0,"k":0,"ix":10},"p":{"a":0,"k":[0.619,-1.238,0],"ix":2,"l":2},"a":{"a":0,"k":[0,0,0],"ix":1,"l":2},"s":{"a":0,"k":[100,100,100],"ix":6,"l":2}},"ao":0,"shapes":[{"ty":"gr","it":[{"d":1,"ty":"el","s":{"a":0,"k":[23.553,23.554],"ix":2},"p":{"a":0,"k":[0,0],"ix":3},"nm":"Ellipse Path 1","mn":"ADBE Vector Shape - Ellipse","hd":false},{"ty":"st","c":{"a":0,"k":[1,1,1,1],"ix":3},"o":{"a":0,"k":100,"ix":4},"w":{"a":0,"k":2,"ix":5},"lc":1,"lj":1,"ml":4,"bm":0,"nm":"Stroke 1","mn":"ADBE Vector Graphic - Stroke","hd":false},{"ty":"tr","p":{"a":0,"k":[0,0],"ix":2},"a":{"a":0,"k":[0,0],"ix":1},"s":{"a":0,"k":[100,100],"ix":3},"r":{"a":0,"k":0,"ix":6},"o":{"a":0,"k":100,"ix":7},"sk":{"a":0,"k":0,"ix":4},"sa":{"a":0,"k":0,"ix":5},"nm":"Transform"}],"nm":"Ellipse 122","np":3,"cix":2,"bm":0,"ix":1,"mn":"ADBE Vector Group","hd":false}],"ip":0,"op":3600,"st":0,"bm":0},{"ddd":0,"ind":27,"ty":4,"nm":"Path 2688","parent":9,"sr":1,"ks":{"o":{"a":0,"k":100,"ix":11},"r":{"a":0,"k":0,"ix":10},"p":{"a":0,"k":[0.383,-0.619,0],"ix":2,"l":2},"a":{"a":0,"k":[27.338,17.475,0],"ix":1,"l":2},"s":{"a":0,"k":[100,100,100],"ix":6,"l":2}},"ao":0,"shapes":[{"ty":"gr","it":[{"ind":0,"ty":"sh","ix":1,"ks":{"a":0,"k":{"i":[[-1.51,2.152],[-14.87,0],[-3.264,-4.999],[1.337,-2.06],[14.441,0],[3.735,5.387]],"o":[[3.533,-5.032],[15.094,0],[1.332,2.041],[-3.471,5.347],[-14.243,0],[-1.508,-2.175]],"v":[[1.114,13.295],[27.575,0],[53.698,13.514],[53.65,20.182],[27.575,34.951],[1.15,20.398]],"c":true},"ix":2},"nm":"Path 1","mn":"ADBE Vector Shape - Group","hd":false},{"ty":"st","c":{"a":0,"k":[0.694117647059,0.396078431373,0.290196078431,1],"ix":3},"o":{"a":0,"k":100,"ix":4},"w":{"a":0,"k":1,"ix":5},"lc":1,"lj":1,"ml":4,"bm":0,"nm":"Stroke 1","mn":"ADBE Vector Graphic - Stroke","hd":false},{"ty":"gf","o":{"a":0,"k":100,"ix":10},"r":1,"bm":0,"g":{"p":3,"k":{"a":0,"k":[0,1,0.533,0.376,0.5,1,0.741,0.441,1,1,0.949,0.506],"ix":9}},"s":{"a":0,"k":[54.5,17.25],"ix":5},"e":{"a":0,"k":[-82,13.25],"ix":6},"t":1,"nm":"Gradient Fill 1","mn":"ADBE Vector Graphic - G-Fill","hd":false},{"ty":"tr","p":{"a":0,"k":[0,0],"ix":2},"a":{"a":0,"k":[0,0],"ix":1},"s":{"a":0,"k":[100,100],"ix":3},"r":{"a":0,"k":0,"ix":6},"o":{"a":0,"k":100,"ix":7},"sk":{"a":0,"k":0,"ix":4},"sa":{"a":0,"k":0,"ix":5},"nm":"Transform"}],"nm":"Path 2688","np":3,"cix":2,"bm":0,"ix":1,"mn":"ADBE Vector Group","hd":false}],"ip":0,"op":3600,"st":0,"bm":0},{"ddd":0,"ind":28,"ty":4,"nm":"Path 2687","parent":1,"sr":1,"ks":{"o":{"a":0,"k":100,"ix":11},"r":{"a":0,"k":0,"ix":10},"p":{"a":0,"k":[74.733,68.954,0],"ix":2,"l":2},"a":{"a":0,"k":[38.513,25.798,0],"ix":1,"l":2},"s":{"a":0,"k":[100,100,100],"ix":6,"l":2}},"ao":0,"shapes":[{"ty":"gr","it":[{"ind":0,"ty":"sh","ix":1,"ks":{"a":0,"k":{"i":[[-0.27,1.414],[0,0],[1.883,0],[0,0],[0.543,-0.899],[0,0],[0,-0.548],[0,0],[-1.657,0],[0,0]],"o":[[0,0],[0.354,-1.849],[0,0],[-1.05,0],[0,0],[-0.283,0.469],[0,0],[0,1.657],[0,0],[1.439,0]],"v":[[68.24,49.159],[76.971,3.564],[74.024,0],[29.562,0],[26.995,1.448],[0.433,45.379],[0,46.932],[0,48.595],[3,51.595],[65.294,51.595]],"c":true},"ix":2},"nm":"Path 1","mn":"ADBE Vector Shape - Group","hd":false},{"ty":"st","c":{"a":0,"k":[0.694117647059,0.396078431373,0.290196078431,1],"ix":3},"o":{"a":0,"k":100,"ix":4},"w":{"a":0,"k":2,"ix":5},"lc":1,"lj":1,"ml":4,"bm":0,"nm":"Stroke 1","mn":"ADBE Vector Graphic - Stroke","hd":false},{"ty":"gf","o":{"a":0,"k":100,"ix":10},"r":1,"bm":0,"g":{"p":3,"k":{"a":0,"k":[0,1,0.533,0.376,0.5,1,0.741,0.441,1,1,0.949,0.506],"ix":9}},"s":{"a":0,"k":[0,0],"ix":5},"e":{"a":0,"k":[100,0],"ix":6},"t":1,"nm":"Gradient Fill 1","mn":"ADBE Vector Graphic - G-Fill","hd":false},{"ty":"tr","p":{"a":0,"k":[0,0],"ix":2},"a":{"a":0,"k":[0,0],"ix":1},"s":{"a":0,"k":[100,100],"ix":3},"r":{"a":0,"k":0,"ix":6},"o":{"a":0,"k":100,"ix":7},"sk":{"a":0,"k":0,"ix":4},"sa":{"a":0,"k":0,"ix":5},"nm":"Transform"}],"nm":"Path 2687","np":3,"cix":2,"bm":0,"ix":1,"mn":"ADBE Vector Group","hd":false}],"ip":0,"op":3600,"st":0,"bm":0},{"ddd":0,"ind":29,"ty":4,"nm":"Path 2686","parent":1,"sr":1,"ks":{"o":{"a":0,"k":100,"ix":11},"r":{"a":0,"k":0,"ix":10},"p":{"a":0,"k":[137.26,52.652,0],"ix":2,"l":2},"a":{"a":0,"k":[11.275,11.276,0],"ix":1,"l":2},"s":{"a":0,"k":[100,100,100],"ix":6,"l":2}},"ao":0,"shapes":[{"ty":"gr","it":[{"ind":0,"ty":"sh","ix":1,"ks":{"a":0,"k":{"i":[[0,0],[0,0],[0,0],[0,0],[0,0],[0,0],[0,0],[0,0],[0,0]],"o":[[0,0],[0,0],[0,0],[0,0],[0,0],[0,0],[0,0],[0,0],[0,0]],"v":[[22.127,1.641],[22.551,0],[20.909,0.423],[1.695,5.382],[0,5.819],[1.238,7.057],[15.494,21.314],[16.731,22.552],[17.169,20.856]],"c":true},"ix":2},"nm":"Path 1","mn":"ADBE Vector Shape - Group","hd":false},{"ty":"st","c":{"a":0,"k":[0.694117647059,0.396078431373,0.290196078431,1],"ix":3},"o":{"a":0,"k":100,"ix":4},"w":{"a":0,"k":2,"ix":5},"lc":1,"lj":1,"ml":4,"bm":0,"nm":"Stroke 1","mn":"ADBE Vector Graphic - Stroke","hd":false},{"ty":"fl","c":{"a":0,"k":[0.996078431373,0.529411764706,0.372549019608,1],"ix":4},"o":{"a":0,"k":100,"ix":5},"r":1,"bm":0,"nm":"Fill 1","mn":"ADBE Vector Graphic - Fill","hd":false},{"ty":"tr","p":{"a":0,"k":[0,0],"ix":2},"a":{"a":0,"k":[0,0],"ix":1},"s":{"a":0,"k":[100,100],"ix":3},"r":{"a":0,"k":0,"ix":6},"o":{"a":0,"k":100,"ix":7},"sk":{"a":0,"k":0,"ix":4},"sa":{"a":0,"k":0,"ix":5},"nm":"Transform"}],"nm":"Path 2686","np":3,"cix":2,"bm":0,"ix":1,"mn":"ADBE Vector Group","hd":false}],"ip":0,"op":3600,"st":0,"bm":0},{"ddd":0,"ind":30,"ty":4,"nm":"Rectangle 1144","parent":1,"sr":1,"ks":{"o":{"a":0,"k":100,"ix":11},"r":{"a":0,"k":0,"ix":10},"p":{"a":0,"k":[163,-2.322,0],"ix":2,"l":2},"a":{"a":0,"k":[0,0,0],"ix":1,"l":2},"s":{"a":0,"k":[100,100,100],"ix":6,"l":2}},"ao":0,"shapes":[{"ty":"gr","it":[{"ty":"rc","d":1,"s":{"a":0,"k":[75.137,19.355],"ix":2},"p":{"a":0,"k":[0,0],"ix":3},"r":{"a":0,"k":9.678,"ix":4},"nm":"Rectangle Path 1","mn":"ADBE Vector Shape - Rect","hd":false},{"ty":"st","c":{"a":0,"k":[0.694117647059,0.396078431373,0.290196078431,1],"ix":3},"o":{"a":0,"k":100,"ix":4},"w":{"a":0,"k":2,"ix":5},"lc":1,"lj":1,"ml":4,"bm":0,"nm":"Stroke 1","mn":"ADBE Vector Graphic - Stroke","hd":false},{"ty":"fl","c":{"a":0,"k":[0.996078431373,0.533333333333,0.376470588235,1],"ix":4},"o":{"a":0,"k":100,"ix":5},"r":1,"bm":0,"nm":"Fill 1","mn":"ADBE Vector Graphic - Fill","hd":false},{"ty":"tr","p":{"a":0,"k":[0,0],"ix":2},"a":{"a":0,"k":[0,0],"ix":1},"s":{"a":0,"k":[100,100],"ix":3},"r":{"a":0,"k":0,"ix":6},"o":{"a":0,"k":100,"ix":7},"sk":{"a":0,"k":0,"ix":4},"sa":{"a":0,"k":0,"ix":5},"nm":"Transform"}],"nm":"Rectangle 1144","np":3,"cix":2,"bm":0,"ix":1,"mn":"ADBE Vector Group","hd":false}],"ip":0,"op":3600,"st":0,"bm":0},{"ddd":0,"ind":31,"ty":4,"nm":"Path 2685","parent":1,"sr":1,"ks":{"o":{"a":0,"k":100,"ix":11},"r":{"a":0,"k":0,"ix":10},"p":{"a":0,"k":[100.038,24.793,0],"ix":2,"l":2},"a":{"a":0,"k":[4.958,5.578,0],"ix":1,"l":2},"s":{"a":0,"k":[100,100,100],"ix":6,"l":2}},"ao":0,"shapes":[{"ty":"gr","it":[{"ind":0,"ty":"sh","ix":1,"ks":{"a":0,"k":{"i":[[0,0],[0,0]],"o":[[0,0],[0,0]],"v":[[4.959,0],[4.959,11.157]],"c":false},"ix":2},"nm":"Path 1","mn":"ADBE Vector Shape - Group","hd":false},{"ind":1,"ty":"sh","ix":2,"ks":{"a":0,"k":{"i":[[0,0],[0,0]],"o":[[0,0],[0,0]],"v":[[0,6.198],[9.917,6.198]],"c":false},"ix":2},"nm":"Path 2","mn":"ADBE Vector Shape - Group","hd":false},{"ty":"st","c":{"a":0,"k":[0.694117647059,0.396078431373,0.290196078431,1],"ix":3},"o":{"a":0,"k":100,"ix":4},"w":{"a":0,"k":2,"ix":5},"lc":2,"lj":1,"ml":4,"bm":0,"nm":"Stroke 1","mn":"ADBE Vector Graphic - Stroke","hd":false},{"ty":"tr","p":{"a":0,"k":[0,0],"ix":2},"a":{"a":0,"k":[0,0],"ix":1},"s":{"a":0,"k":[100,100],"ix":3},"r":{"a":0,"k":0,"ix":6},"o":{"a":0,"k":100,"ix":7},"sk":{"a":0,"k":0,"ix":4},"sa":{"a":0,"k":0,"ix":5},"nm":"Transform"}],"nm":"Path 2685","np":4,"cix":2,"bm":0,"ix":1,"mn":"ADBE Vector Group","hd":false}],"ip":0,"op":3600,"st":0,"bm":0},{"ddd":0,"ind":32,"ty":4,"nm":"Path 2684","parent":1,"sr":1,"ks":{"o":{"a":0,"k":100,"ix":11},"r":{"a":1,"k":[{"i":{"x":[0.667],"y":[1]},"o":{"x":[0.333],"y":[0]},"t":30,"s":[0]},{"i":{"x":[0.667],"y":[1]},"o":{"x":[0.333],"y":[0]},"t":60,"s":[-9]},{"t":90,"s":[0]}],"ix":10},"p":{"a":0,"k":[49.593,37.576,0],"ix":2,"l":2},"a":{"a":0,"k":[18.115,33.616,0],"ix":1,"l":2},"s":{"a":0,"k":[100,100,100],"ix":6,"l":2}},"ao":0,"shapes":[{"ty":"gr","it":[{"ind":0,"ty":"sh","ix":1,"ks":{"a":0,"k":{"i":[[-9.453,0],[0,9.452],[9.452,0],[0,-9.453]],"o":[[9.452,0],[0,-9.453],[-9.453,0],[0,9.452]],"v":[[17.115,34.231],[34.23,17.116],[17.115,0],[0,17.116]],"c":true},"ix":2},"nm":"Path 1","mn":"ADBE Vector Shape - Group","hd":false},{"ty":"st","c":{"a":0,"k":[0.694117647059,0.396078431373,0.290196078431,1],"ix":3},"o":{"a":0,"k":100,"ix":4},"w":{"a":0,"k":2,"ix":5},"lc":1,"lj":1,"ml":4,"bm":0,"nm":"Stroke 1","mn":"ADBE Vector Graphic - Stroke","hd":false},{"ty":"gf","o":{"a":0,"k":100,"ix":10},"r":1,"bm":0,"g":{"p":3,"k":{"a":0,"k":[0,1,0.533,0.376,0.5,1,0.741,0.441,1,1,0.949,0.506],"ix":9}},"s":{"a":0,"k":[0,0],"ix":5},"e":{"a":0,"k":[100,0],"ix":6},"t":1,"nm":"Gradient Fill 1","mn":"ADBE Vector Graphic - G-Fill","hd":false},{"ty":"tr","p":{"a":0,"k":[0,0],"ix":2},"a":{"a":0,"k":[0,0],"ix":1},"s":{"a":0,"k":[100,100],"ix":3},"r":{"a":0,"k":0,"ix":6},"o":{"a":0,"k":100,"ix":7},"sk":{"a":0,"k":0,"ix":4},"sa":{"a":0,"k":0,"ix":5},"nm":"Transform"}],"nm":"Path 2684","np":3,"cix":2,"bm":0,"ix":1,"mn":"ADBE Vector Group","hd":false}],"ip":0,"op":3600,"st":0,"bm":0},{"ddd":0,"ind":33,"ty":4,"nm":"Path 2683","parent":1,"sr":1,"ks":{"o":{"a":0,"k":100,"ix":11},"r":{"a":0,"k":0,"ix":10},"p":{"a":0,"k":[47.665,60.431,0],"ix":2,"l":2},"a":{"a":0,"k":[24.863,18.666,0],"ix":1,"l":2},"s":{"a":0,"k":[100,100,100],"ix":6,"l":2}},"ao":0,"shapes":[{"ty":"gr","it":[{"ind":0,"ty":"sh","ix":1,"ks":{"a":0,"k":{"i":[[0,0],[0,0],[0,0],[0,0]],"o":[[0,0],[0,0],[0,0],[0,0]],"v":[[1,12.777],[0.006,12.673],[0,12.725],[0,12.777]],"c":true},"ix":2},"nm":"Path 1","mn":"ADBE Vector Shape - Group","hd":false},{"ind":1,"ty":"sh","ix":2,"ks":{"a":0,"k":{"i":[[0,0],[-0.485,0.264],[0.265,0.485]],"o":[[0.265,0.484],[0.485,-0.265],[0,0]],"v":[[47.847,8.298],[49.204,8.697],[49.603,7.34]],"c":true},"ix":2},"nm":"Path 2","mn":"ADBE Vector Shape - Group","hd":false},{"ind":2,"ty":"sh","ix":3,"ks":{"a":0,"k":{"i":[[0,0],[0,0]],"o":[[0,0],[0,0]],"v":[[3.789,33.542],[3.082,34.249]],"c":true},"ix":2},"nm":"Path 3","mn":"ADBE Vector Shape - Group","hd":false},{"ind":3,"ty":"sh","ix":4,"ks":{"a":0,"k":{"i":[[0,0],[0,0],[0,0],[0,0]],"o":[[0,0],[0,0],[0,0],[0,0]],"v":[[20.834,35.331],[10.523,35.331],[10.523,37.331],[20.834,37.331]],"c":true},"ix":2},"nm":"Path 4","mn":"ADBE Vector Shape - Group","hd":false},{"ind":4,"ty":"sh","ix":5,"ks":{"a":0,"k":{"i":[[0,0],[0,0],[0,0],[0,0]],"o":[[0,0],[0,0],[0,0],[0,0]],"v":[[2,26.808],[2,12.777],[0,12.777],[0,26.808]],"c":true},"ix":2},"nm":"Path 5","mn":"ADBE Vector Shape - Group","hd":false},{"ind":5,"ty":"sh","ix":6,"ks":{"a":0,"k":{"i":[[-0.994,-0.104],[0,-0.001],[0.001,0],[-0.001,0],[0,0.001],[-0.001,0.009],[-0.005,0.038],[-0.025,0.151],[-0.124,0.525],[-0.691,1.382],[-4.118,0.001],[0,0],[1.56,-3.121],[0.273,-1.153],[0.056,-0.343],[0.012,-0.096],[0.003,-0.026],[0.001,-0.008],[0,-0.002],[0,-0.001],[0,0]],"o":[[0.995,0.105],[0,0],[0,0],[0,0],[0,-0.004],[0.002,-0.018],[0.01,-0.078],[0.048,-0.302],[0.25,-1.055],[1.384,-2.767],[0,0],[-5.179,0.001],[-0.781,1.562],[-0.137,0.579],[-0.027,0.171],[-0.006,0.047],[-0.002,0.014],[0,0.004],[0,0.002],[0,0],[0,0]],"v":[[1,12.777],[1.995,12.883],[1.994,12.883],[1.995,12.883],[1.995,12.88],[1.997,12.861],[2.008,12.776],[2.059,12.431],[2.312,11.168],[3.676,7.337],[11.537,2],[11.537,0],[1.888,6.442],[0.366,10.707],[0.084,12.112],[0.025,12.515],[0.011,12.626],[0.007,12.658],[0.006,12.667],[0.006,12.671],[0.006,12.672]],"c":true},"ix":2},"nm":"Path 6","mn":"ADBE Vector Shape - Group","hd":false},{"ind":6,"ty":"sh","ix":7,"ks":{"a":0,"k":{"i":[[0,0],[-7.438,0],[0,0],[9.297,-0.001]],"o":[[9.297,-0.001],[0,0],[-7.438,0],[0,0]],"v":[[11.537,2],[37.569,2],[37.569,0],[11.537,0]],"c":true},"ix":2},"nm":"Path 7","mn":"ADBE Vector Shape - Group","hd":false},{"ind":7,"ty":"sh","ix":8,"ks":{"a":0,"k":{"i":[[0,0],[-1.741,-1.597],[-0.435,-0.598],[-0.105,-0.169],[-0.024,-0.042],[-0.005,-0.009],[-0.001,-0.001],[0,0],[0,0],[0,0],[-0.878,0.479],[0,0],[0,0],[0,0.001],[0.002,0.003],[0.005,0.008],[0.017,0.029],[0.063,0.102],[0.248,0.341],[0.989,0.907],[4.047,0]],"o":[[3.391,0],[0.87,0.797],[0.217,0.299],[0.053,0.084],[0.013,0.021],[0.003,0.004],[0,0.001],[0,0],[0,0],[0,0],[0.878,-0.479],[0,0],[0,-0.001],[-0.001,-0.002],[-0.003,-0.005],[-0.01,-0.017],[-0.034,-0.058],[-0.128,-0.205],[-0.495,-0.68],[-1.977,-1.812],[0,0]],"v":[[37.569,2],[45.26,5.147],[47.219,7.341],[47.702,8.055],[47.817,8.245],[47.843,8.29],[47.848,8.298],[47.848,8.299],[47.848,8.299],[47.848,8.298],[48.725,7.819],[49.603,7.339],[49.602,7.338],[49.601,7.336],[49.597,7.329],[49.586,7.309],[49.546,7.239],[49.4,6.997],[48.837,6.165],[46.612,3.672],[37.569,0]],"c":true},"ix":2},"nm":"Path 8","mn":"ADBE Vector Shape - Group","hd":false},{"ind":8,"ty":"sh","ix":9,"ks":{"a":0,"k":{"i":[[0,0],[0,2.261],[0,0],[-1.973,-1.974]],"o":[[-1.598,-1.599],[0,0],[0,2.791],[0,0]],"v":[[4.496,32.835],[2,26.808],[0,26.808],[3.082,34.249]],"c":true},"ix":2},"nm":"Path 9","mn":"ADBE Vector Shape - Group","hd":false},{"ind":9,"ty":"sh","ix":10,"ks":{"a":0,"k":{"i":[[0,0],[1.599,1.598],[0,0],[-2.791,0]],"o":[[-2.26,0],[0,0],[1.973,1.973],[0,0]],"v":[[10.523,35.331],[4.496,32.835],[3.082,34.249],[10.523,37.331]],"c":true},"ix":2},"nm":"Path 10","mn":"ADBE Vector Shape - Group","hd":false},{"ty":"fl","c":{"a":0,"k":[0.694117647059,0.396078431373,0.290196078431,1],"ix":4},"o":{"a":0,"k":100,"ix":5},"r":1,"bm":0,"nm":"Fill 1","mn":"ADBE Vector Graphic - Fill","hd":false},{"ty":"tr","p":{"a":0,"k":[0,0],"ix":2},"a":{"a":0,"k":[0,0],"ix":1},"s":{"a":0,"k":[100,100],"ix":3},"r":{"a":0,"k":0,"ix":6},"o":{"a":0,"k":100,"ix":7},"sk":{"a":0,"k":0,"ix":4},"sa":{"a":0,"k":0,"ix":5},"nm":"Transform"}],"nm":"Path 2683","np":12,"cix":2,"bm":0,"ix":1,"mn":"ADBE Vector Group","hd":false}],"ip":0,"op":3600,"st":0,"bm":0},{"ddd":0,"ind":34,"ty":4,"nm":"processor","parent":1,"sr":1,"ks":{"o":{"a":0,"k":100,"ix":11},"r":{"a":0,"k":0,"ix":10},"p":{"a":1,"k":[{"i":{"x":0.667,"y":1},"o":{"x":0.333,"y":0},"t":0,"s":[-76.296,-20.767,0],"to":[0,0,0],"ti":[0,0,0]},{"i":{"x":0.667,"y":1},"o":{"x":0.333,"y":0},"t":60,"s":[-76.296,-29.742,0],"to":[0,0,0],"ti":[0,0,0]},{"t":120,"s":[-76.296,-20.767,0]}],"ix":2,"l":2},"a":{"a":0,"k":[0,0,0],"ix":1,"l":2},"s":{"a":0,"k":[100,100,100],"ix":6,"l":2}},"ao":0,"shapes":[{"ty":"rc","d":1,"s":{"a":0,"k":[97.311,97.313],"ix":2},"p":{"a":0,"k":[0,0],"ix":3},"r":{"a":0,"k":0,"ix":4},"nm":"Rectangle Path 1","mn":"ADBE Vector Shape - Rect","hd":false}],"ip":0,"op":3600,"st":0,"bm":0},{"ddd":0,"ind":35,"ty":4,"nm":"Rectangle 1143","parent":34,"sr":1,"ks":{"o":{"a":0,"k":100,"ix":11},"r":{"a":0,"k":0,"ix":10},"p":{"a":0,"k":[-0.93,-0.93,0],"ix":2,"l":2},"a":{"a":0,"k":[0,0,0],"ix":1,"l":2},"s":{"a":0,"k":[100,100,100],"ix":6,"l":2}},"ao":0,"shapes":[{"ty":"gr","it":[{"ty":"rc","d":1,"s":{"a":0,"k":[53.783,53.785],"ix":2},"p":{"a":0,"k":[0,0],"ix":3},"r":{"a":0,"k":9,"ix":4},"nm":"Rectangle Path 1","mn":"ADBE Vector Shape - Rect","hd":false},{"ty":"fl","c":{"a":0,"k":[1,1,1,1],"ix":4},"o":{"a":0,"k":100,"ix":5},"r":1,"bm":0,"nm":"Fill 1","mn":"ADBE Vector Graphic - Fill","hd":false},{"ty":"tr","p":{"a":0,"k":[0,0],"ix":2},"a":{"a":0,"k":[0,0],"ix":1},"s":{"a":0,"k":[100,100],"ix":3},"r":{"a":0,"k":0,"ix":6},"o":{"a":0,"k":100,"ix":7},"sk":{"a":0,"k":0,"ix":4},"sa":{"a":0,"k":0,"ix":5},"nm":"Transform"}],"nm":"Rectangle 1143","np":3,"cix":2,"bm":0,"ix":1,"mn":"ADBE Vector Group","hd":false}],"ip":0,"op":3600,"st":0,"bm":0},{"ddd":0,"ind":36,"ty":4,"nm":"Rectangle 1142","parent":34,"sr":1,"ks":{"o":{"a":0,"k":100,"ix":11},"r":{"a":0,"k":0,"ix":10},"p":{"a":0,"k":[-0.93,-0.929,0],"ix":2,"l":2},"a":{"a":0,"k":[0,0,0],"ix":1,"l":2},"s":{"a":0,"k":[100,100,100],"ix":6,"l":2}},"ao":0,"shapes":[{"ty":"gr","it":[{"ty":"rc","d":1,"s":{"a":0,"k":[78.096,78.099],"ix":2},"p":{"a":0,"k":[0,0],"ix":3},"r":{"a":0,"k":8,"ix":4},"nm":"Rectangle Path 1","mn":"ADBE Vector Shape - Rect","hd":false},{"ty":"fl","c":{"a":0,"k":[0.694117647059,0.396078431373,0.294117647059,1],"ix":4},"o":{"a":0,"k":100,"ix":5},"r":1,"bm":0,"nm":"Fill 1","mn":"ADBE Vector Graphic - Fill","hd":false},{"ty":"tr","p":{"a":0,"k":[0,0],"ix":2},"a":{"a":0,"k":[0,0],"ix":1},"s":{"a":0,"k":[100,100],"ix":3},"r":{"a":0,"k":0,"ix":6},"o":{"a":0,"k":100,"ix":7},"sk":{"a":0,"k":0,"ix":4},"sa":{"a":0,"k":0,"ix":5},"nm":"Transform"}],"nm":"Rectangle 1142","np":3,"cix":2,"bm":0,"ix":1,"mn":"ADBE Vector Group","hd":false}],"ip":0,"op":3600,"st":0,"bm":0},{"ddd":0,"ind":37,"ty":4,"nm":"Path 2682","parent":34,"sr":1,"ks":{"o":{"a":0,"k":100,"ix":11},"r":{"a":0,"k":0,"ix":10},"p":{"a":0,"k":[0,24.488,0],"ix":2,"l":2},"a":{"a":0,"k":[48.655,0,0],"ix":1,"l":2},"s":{"a":0,"k":[100,100,100],"ix":6,"l":2}},"ao":0,"shapes":[{"ty":"gr","it":[{"ind":0,"ty":"sh","ix":1,"ks":{"a":0,"k":{"i":[[0,0],[0,0]],"o":[[0,0],[0,0]],"v":[[97.31,0],[0,0]],"c":false},"ix":2},"nm":"Path 1","mn":"ADBE Vector Shape - Group","hd":false},{"ty":"st","c":{"a":0,"k":[0.694117647059,0.396078431373,0.290196078431,1],"ix":3},"o":{"a":0,"k":100,"ix":4},"w":{"a":0,"k":2,"ix":5},"lc":1,"lj":1,"ml":4,"bm":0,"nm":"Stroke 1","mn":"ADBE Vector Graphic - Stroke","hd":false},{"ty":"tr","p":{"a":0,"k":[0,0],"ix":2},"a":{"a":0,"k":[0,0],"ix":1},"s":{"a":0,"k":[100,100],"ix":3},"r":{"a":0,"k":0,"ix":6},"o":{"a":0,"k":100,"ix":7},"sk":{"a":0,"k":0,"ix":4},"sa":{"a":0,"k":0,"ix":5},"nm":"Transform"}],"nm":"Path 2682","np":3,"cix":2,"bm":0,"ix":1,"mn":"ADBE Vector Group","hd":false}],"ip":0,"op":3600,"st":0,"bm":0},{"ddd":0,"ind":38,"ty":4,"nm":"Path 2681","parent":34,"sr":1,"ks":{"o":{"a":0,"k":100,"ix":11},"r":{"a":0,"k":0,"ix":10},"p":{"a":0,"k":[0,12.091,0],"ix":2,"l":2},"a":{"a":0,"k":[48.655,0,0],"ix":1,"l":2},"s":{"a":0,"k":[100,100,100],"ix":6,"l":2}},"ao":0,"shapes":[{"ty":"gr","it":[{"ind":0,"ty":"sh","ix":1,"ks":{"a":0,"k":{"i":[[0,0],[0,0]],"o":[[0,0],[0,0]],"v":[[97.31,0],[0,0]],"c":false},"ix":2},"nm":"Path 1","mn":"ADBE Vector Shape - Group","hd":false},{"ty":"st","c":{"a":0,"k":[0.694117647059,0.396078431373,0.290196078431,1],"ix":3},"o":{"a":0,"k":100,"ix":4},"w":{"a":0,"k":2,"ix":5},"lc":1,"lj":1,"ml":4,"bm":0,"nm":"Stroke 1","mn":"ADBE Vector Graphic - Stroke","hd":false},{"ty":"tr","p":{"a":0,"k":[0,0],"ix":2},"a":{"a":0,"k":[0,0],"ix":1},"s":{"a":0,"k":[100,100],"ix":3},"r":{"a":0,"k":0,"ix":6},"o":{"a":0,"k":100,"ix":7},"sk":{"a":0,"k":0,"ix":4},"sa":{"a":0,"k":0,"ix":5},"nm":"Transform"}],"nm":"Path 2681","np":3,"cix":2,"bm":0,"ix":1,"mn":"ADBE Vector Group","hd":false}],"ip":0,"op":3600,"st":0,"bm":0},{"ddd":0,"ind":39,"ty":4,"nm":"Path 2680","parent":34,"sr":1,"ks":{"o":{"a":0,"k":100,"ix":11},"r":{"a":0,"k":0,"ix":10},"p":{"a":0,"k":[0,-0.309,0],"ix":2,"l":2},"a":{"a":0,"k":[48.655,0,0],"ix":1,"l":2},"s":{"a":0,"k":[100,100,100],"ix":6,"l":2}},"ao":0,"shapes":[{"ty":"gr","it":[{"ind":0,"ty":"sh","ix":1,"ks":{"a":0,"k":{"i":[[0,0],[0,0]],"o":[[0,0],[0,0]],"v":[[97.31,0],[0,0]],"c":false},"ix":2},"nm":"Path 1","mn":"ADBE Vector Shape - Group","hd":false},{"ty":"st","c":{"a":0,"k":[0.694117647059,0.396078431373,0.290196078431,1],"ix":3},"o":{"a":0,"k":100,"ix":4},"w":{"a":0,"k":2,"ix":5},"lc":1,"lj":1,"ml":4,"bm":0,"nm":"Stroke 1","mn":"ADBE Vector Graphic - Stroke","hd":false},{"ty":"tr","p":{"a":0,"k":[0,0],"ix":2},"a":{"a":0,"k":[0,0],"ix":1},"s":{"a":0,"k":[100,100],"ix":3},"r":{"a":0,"k":0,"ix":6},"o":{"a":0,"k":100,"ix":7},"sk":{"a":0,"k":0,"ix":4},"sa":{"a":0,"k":0,"ix":5},"nm":"Transform"}],"nm":"Path 2680","np":3,"cix":2,"bm":0,"ix":1,"mn":"ADBE Vector Group","hd":false}],"ip":0,"op":3600,"st":0,"bm":0},{"ddd":0,"ind":40,"ty":4,"nm":"Path 2679","parent":34,"sr":1,"ks":{"o":{"a":0,"k":100,"ix":11},"r":{"a":0,"k":0,"ix":10},"p":{"a":0,"k":[0,-12.706,0],"ix":2,"l":2},"a":{"a":0,"k":[48.655,0,0],"ix":1,"l":2},"s":{"a":0,"k":[100,100,100],"ix":6,"l":2}},"ao":0,"shapes":[{"ty":"gr","it":[{"ind":0,"ty":"sh","ix":1,"ks":{"a":0,"k":{"i":[[0,0],[0,0]],"o":[[0,0],[0,0]],"v":[[97.31,0],[0,0]],"c":false},"ix":2},"nm":"Path 1","mn":"ADBE Vector Shape - Group","hd":false},{"ty":"st","c":{"a":0,"k":[0.694117647059,0.396078431373,0.290196078431,1],"ix":3},"o":{"a":0,"k":100,"ix":4},"w":{"a":0,"k":2,"ix":5},"lc":1,"lj":1,"ml":4,"bm":0,"nm":"Stroke 1","mn":"ADBE Vector Graphic - Stroke","hd":false},{"ty":"tr","p":{"a":0,"k":[0,0],"ix":2},"a":{"a":0,"k":[0,0],"ix":1},"s":{"a":0,"k":[100,100],"ix":3},"r":{"a":0,"k":0,"ix":6},"o":{"a":0,"k":100,"ix":7},"sk":{"a":0,"k":0,"ix":4},"sa":{"a":0,"k":0,"ix":5},"nm":"Transform"}],"nm":"Path 2679","np":3,"cix":2,"bm":0,"ix":1,"mn":"ADBE Vector Group","hd":false}],"ip":0,"op":3600,"st":0,"bm":0},{"ddd":0,"ind":41,"ty":4,"nm":"Path 2678","parent":34,"sr":1,"ks":{"o":{"a":0,"k":100,"ix":11},"r":{"a":0,"k":0,"ix":10},"p":{"a":0,"k":[0,-24.481,0],"ix":2,"l":2},"a":{"a":0,"k":[48.655,0,0],"ix":1,"l":2},"s":{"a":0,"k":[100,100,100],"ix":6,"l":2}},"ao":0,"shapes":[{"ty":"gr","it":[{"ind":0,"ty":"sh","ix":1,"ks":{"a":0,"k":{"i":[[0,0],[0,0]],"o":[[0,0],[0,0]],"v":[[97.31,0],[0,0]],"c":false},"ix":2},"nm":"Path 1","mn":"ADBE Vector Shape - Group","hd":false},{"ty":"st","c":{"a":0,"k":[0.694117647059,0.396078431373,0.290196078431,1],"ix":3},"o":{"a":0,"k":100,"ix":4},"w":{"a":0,"k":2,"ix":5},"lc":1,"lj":1,"ml":4,"bm":0,"nm":"Stroke 1","mn":"ADBE Vector Graphic - Stroke","hd":false},{"ty":"tr","p":{"a":0,"k":[0,0],"ix":2},"a":{"a":0,"k":[0,0],"ix":1},"s":{"a":0,"k":[100,100],"ix":3},"r":{"a":0,"k":0,"ix":6},"o":{"a":0,"k":100,"ix":7},"sk":{"a":0,"k":0,"ix":4},"sa":{"a":0,"k":0,"ix":5},"nm":"Transform"}],"nm":"Path 2678","np":3,"cix":2,"bm":0,"ix":1,"mn":"ADBE Vector Group","hd":false}],"ip":0,"op":3600,"st":0,"bm":0},{"ddd":0,"ind":42,"ty":4,"nm":"Path 2677","parent":34,"sr":1,"ks":{"o":{"a":0,"k":100,"ix":11},"r":{"a":0,"k":0,"ix":10},"p":{"a":0,"k":[24.481,0,0],"ix":2,"l":2},"a":{"a":0,"k":[0,48.657,0],"ix":1,"l":2},"s":{"a":0,"k":[100,100,100],"ix":6,"l":2}},"ao":0,"shapes":[{"ty":"gr","it":[{"ind":0,"ty":"sh","ix":1,"ks":{"a":0,"k":{"i":[[0,0],[0,0]],"o":[[0,0],[0,0]],"v":[[0,0],[0,97.314]],"c":false},"ix":2},"nm":"Path 1","mn":"ADBE Vector Shape - Group","hd":false},{"ty":"st","c":{"a":0,"k":[0.694117647059,0.396078431373,0.290196078431,1],"ix":3},"o":{"a":0,"k":100,"ix":4},"w":{"a":0,"k":2,"ix":5},"lc":1,"lj":1,"ml":4,"bm":0,"nm":"Stroke 1","mn":"ADBE Vector Graphic - Stroke","hd":false},{"ty":"tr","p":{"a":0,"k":[0,0],"ix":2},"a":{"a":0,"k":[0,0],"ix":1},"s":{"a":0,"k":[100,100],"ix":3},"r":{"a":0,"k":0,"ix":6},"o":{"a":0,"k":100,"ix":7},"sk":{"a":0,"k":0,"ix":4},"sa":{"a":0,"k":0,"ix":5},"nm":"Transform"}],"nm":"Path 2677","np":3,"cix":2,"bm":0,"ix":1,"mn":"ADBE Vector Group","hd":false}],"ip":0,"op":3600,"st":0,"bm":0},{"ddd":0,"ind":43,"ty":4,"nm":"Path 2676","parent":34,"sr":1,"ks":{"o":{"a":0,"k":100,"ix":11},"r":{"a":0,"k":0,"ix":10},"p":{"a":0,"k":[12.084,0,0],"ix":2,"l":2},"a":{"a":0,"k":[0,48.657,0],"ix":1,"l":2},"s":{"a":0,"k":[100,100,100],"ix":6,"l":2}},"ao":0,"shapes":[{"ty":"gr","it":[{"ind":0,"ty":"sh","ix":1,"ks":{"a":0,"k":{"i":[[0,0],[0,0]],"o":[[0,0],[0,0]],"v":[[0,0],[0,97.314]],"c":false},"ix":2},"nm":"Path 1","mn":"ADBE Vector Shape - Group","hd":false},{"ty":"st","c":{"a":0,"k":[0.694117647059,0.396078431373,0.290196078431,1],"ix":3},"o":{"a":0,"k":100,"ix":4},"w":{"a":0,"k":2,"ix":5},"lc":1,"lj":1,"ml":4,"bm":0,"nm":"Stroke 1","mn":"ADBE Vector Graphic - Stroke","hd":false},{"ty":"tr","p":{"a":0,"k":[0,0],"ix":2},"a":{"a":0,"k":[0,0],"ix":1},"s":{"a":0,"k":[100,100],"ix":3},"r":{"a":0,"k":0,"ix":6},"o":{"a":0,"k":100,"ix":7},"sk":{"a":0,"k":0,"ix":4},"sa":{"a":0,"k":0,"ix":5},"nm":"Transform"}],"nm":"Path 2676","np":3,"cix":2,"bm":0,"ix":1,"mn":"ADBE Vector Group","hd":false}],"ip":0,"op":3600,"st":0,"bm":0},{"ddd":0,"ind":44,"ty":4,"nm":"Path 2675","parent":34,"sr":1,"ks":{"o":{"a":0,"k":100,"ix":11},"r":{"a":0,"k":0,"ix":10},"p":{"a":0,"k":[-0.312,0,0],"ix":2,"l":2},"a":{"a":0,"k":[0,48.657,0],"ix":1,"l":2},"s":{"a":0,"k":[100,100,100],"ix":6,"l":2}},"ao":0,"shapes":[{"ty":"gr","it":[{"ind":0,"ty":"sh","ix":1,"ks":{"a":0,"k":{"i":[[0,0],[0,0]],"o":[[0,0],[0,0]],"v":[[0,0],[0,97.314]],"c":false},"ix":2},"nm":"Path 1","mn":"ADBE Vector Shape - Group","hd":false},{"ty":"st","c":{"a":0,"k":[0.694117647059,0.396078431373,0.290196078431,1],"ix":3},"o":{"a":0,"k":100,"ix":4},"w":{"a":0,"k":2,"ix":5},"lc":1,"lj":1,"ml":4,"bm":0,"nm":"Stroke 1","mn":"ADBE Vector Graphic - Stroke","hd":false},{"ty":"tr","p":{"a":0,"k":[0,0],"ix":2},"a":{"a":0,"k":[0,0],"ix":1},"s":{"a":0,"k":[100,100],"ix":3},"r":{"a":0,"k":0,"ix":6},"o":{"a":0,"k":100,"ix":7},"sk":{"a":0,"k":0,"ix":4},"sa":{"a":0,"k":0,"ix":5},"nm":"Transform"}],"nm":"Path 2675","np":3,"cix":2,"bm":0,"ix":1,"mn":"ADBE Vector Group","hd":false}],"ip":0,"op":3600,"st":0,"bm":0},{"ddd":0,"ind":45,"ty":4,"nm":"Path 2674","parent":34,"sr":1,"ks":{"o":{"a":0,"k":100,"ix":11},"r":{"a":0,"k":0,"ix":10},"p":{"a":0,"k":[-12.709,0,0],"ix":2,"l":2},"a":{"a":0,"k":[0,48.657,0],"ix":1,"l":2},"s":{"a":0,"k":[100,100,100],"ix":6,"l":2}},"ao":0,"shapes":[{"ty":"gr","it":[{"ind":0,"ty":"sh","ix":1,"ks":{"a":0,"k":{"i":[[0,0],[0,0]],"o":[[0,0],[0,0]],"v":[[0,0],[0,97.314]],"c":false},"ix":2},"nm":"Path 1","mn":"ADBE Vector Shape - Group","hd":false},{"ty":"st","c":{"a":0,"k":[0.694117647059,0.396078431373,0.290196078431,1],"ix":3},"o":{"a":0,"k":100,"ix":4},"w":{"a":0,"k":2,"ix":5},"lc":1,"lj":1,"ml":4,"bm":0,"nm":"Stroke 1","mn":"ADBE Vector Graphic - Stroke","hd":false},{"ty":"tr","p":{"a":0,"k":[0,0],"ix":2},"a":{"a":0,"k":[0,0],"ix":1},"s":{"a":0,"k":[100,100],"ix":3},"r":{"a":0,"k":0,"ix":6},"o":{"a":0,"k":100,"ix":7},"sk":{"a":0,"k":0,"ix":4},"sa":{"a":0,"k":0,"ix":5},"nm":"Transform"}],"nm":"Path 2674","np":3,"cix":2,"bm":0,"ix":1,"mn":"ADBE Vector Group","hd":false}],"ip":0,"op":3600,"st":0,"bm":0},{"ddd":0,"ind":46,"ty":4,"nm":"Path 2673","parent":34,"sr":1,"ks":{"o":{"a":0,"k":100,"ix":11},"r":{"a":0,"k":0,"ix":10},"p":{"a":0,"k":[-24.484,0,0],"ix":2,"l":2},"a":{"a":0,"k":[0,48.657,0],"ix":1,"l":2},"s":{"a":0,"k":[100,100,100],"ix":6,"l":2}},"ao":0,"shapes":[{"ty":"gr","it":[{"ind":0,"ty":"sh","ix":1,"ks":{"a":0,"k":{"i":[[0,0],[0,0]],"o":[[0,0],[0,0]],"v":[[0,0],[0,97.314]],"c":false},"ix":2},"nm":"Path 1","mn":"ADBE Vector Shape - Group","hd":false},{"ty":"st","c":{"a":0,"k":[0.694117647059,0.396078431373,0.290196078431,1],"ix":3},"o":{"a":0,"k":100,"ix":4},"w":{"a":0,"k":2,"ix":5},"lc":1,"lj":1,"ml":4,"bm":0,"nm":"Stroke 1","mn":"ADBE Vector Graphic - Stroke","hd":false},{"ty":"tr","p":{"a":0,"k":[0,0],"ix":2},"a":{"a":0,"k":[0,0],"ix":1},"s":{"a":0,"k":[100,100],"ix":3},"r":{"a":0,"k":0,"ix":6},"o":{"a":0,"k":100,"ix":7},"sk":{"a":0,"k":0,"ix":4},"sa":{"a":0,"k":0,"ix":5},"nm":"Transform"}],"nm":"Path 2673","np":3,"cix":2,"bm":0,"ix":1,"mn":"ADBE Vector Group","hd":false}],"ip":0,"op":3600,"st":0,"bm":0},{"ddd":0,"ind":47,"ty":4,"nm":"bag","parent":1,"sr":1,"ks":{"o":{"a":0,"k":100,"ix":11},"r":{"a":0,"k":0,"ix":10},"p":{"a":0,"k":[-59.113,69.42,0],"ix":2,"l":2},"a":{"a":0,"k":[0,0,0],"ix":1,"l":2},"s":{"a":0,"k":[100,100,100],"ix":6,"l":2}},"ao":0,"shapes":[{"ty":"rc","d":1,"s":{"a":0,"k":[36.465,33.711],"ix":2},"p":{"a":0,"k":[0,0],"ix":3},"r":{"a":0,"k":0,"ix":4},"nm":"Rectangle Path 1","mn":"ADBE Vector Shape - Rect","hd":false}],"ip":0,"op":3600,"st":0,"bm":0},{"ddd":0,"ind":48,"ty":4,"nm":"Path 2672","parent":47,"sr":1,"ks":{"o":{"a":0,"k":100,"ix":11},"r":{"a":0,"k":0,"ix":10},"p":{"a":0,"k":[-0.139,-14.256,0],"ix":2,"l":2},"a":{"a":0,"k":[6.938,2.6,0],"ix":1,"l":2},"s":{"a":0,"k":[100,100,100],"ix":6,"l":2}},"ao":0,"shapes":[{"ty":"gr","it":[{"ind":0,"ty":"sh","ix":1,"ks":{"a":0,"k":{"i":[[-2.836,0],[0,0],[0,-2.836],[0.035,0],[0,0],[0,0.035]],"o":[[0,0],[2.836,0],[0,0.035],[0,0],[-0.035,0],[0,-2.836]],"v":[[5.135,0],[8.74,0],[13.875,5.135],[13.812,5.199],[0.063,5.199],[0,5.135]],"c":true},"ix":2},"nm":"Path 1","mn":"ADBE Vector Shape - Group","hd":false},{"ty":"st","c":{"a":0,"k":[0.694117647059,0.396078431373,0.290196078431,1],"ix":3},"o":{"a":0,"k":100,"ix":4},"w":{"a":0,"k":1,"ix":5},"lc":1,"lj":1,"ml":4,"bm":0,"nm":"Stroke 1","mn":"ADBE Vector Graphic - Stroke","hd":false},{"ty":"fl","c":{"a":0,"k":[1,0.533333333333,0.372549019608,1],"ix":4},"o":{"a":0,"k":100,"ix":5},"r":1,"bm":0,"nm":"Fill 1","mn":"ADBE Vector Graphic - Fill","hd":false},{"ty":"tr","p":{"a":0,"k":[0,0],"ix":2},"a":{"a":0,"k":[0,0],"ix":1},"s":{"a":0,"k":[100,100],"ix":3},"r":{"a":0,"k":0,"ix":6},"o":{"a":0,"k":100,"ix":7},"sk":{"a":0,"k":0,"ix":4},"sa":{"a":0,"k":0,"ix":5},"nm":"Transform"}],"nm":"Path 2672","np":3,"cix":2,"bm":0,"ix":1,"mn":"ADBE Vector Group","hd":false}],"ip":0,"op":3600,"st":0,"bm":0},{"ddd":0,"ind":49,"ty":4,"nm":"Rectangle 1141","parent":47,"sr":1,"ks":{"o":{"a":0,"k":100,"ix":11},"r":{"a":0,"k":0,"ix":10},"p":{"a":0,"k":[-0.139,1.86,0],"ix":2,"l":2},"a":{"a":0,"k":[0,0,0],"ix":1,"l":2},"s":{"a":0,"k":[100,100,100],"ix":6,"l":2}},"ao":0,"shapes":[{"ty":"gr","it":[{"ty":"rc","d":1,"s":{"a":0,"k":[5.438,9.157],"ix":2},"p":{"a":0,"k":[0,0],"ix":3},"r":{"a":0,"k":2.719,"ix":4},"nm":"Rectangle Path 1","mn":"ADBE Vector Shape - Rect","hd":false},{"ty":"st","c":{"a":0,"k":[0.694117647059,0.396078431373,0.290196078431,1],"ix":3},"o":{"a":0,"k":100,"ix":4},"w":{"a":0,"k":2,"ix":5},"lc":1,"lj":1,"ml":4,"bm":0,"nm":"Stroke 1","mn":"ADBE Vector Graphic - Stroke","hd":false},{"ty":"fl","c":{"a":0,"k":[1,1,1,1],"ix":4},"o":{"a":0,"k":100,"ix":5},"r":1,"bm":0,"nm":"Fill 1","mn":"ADBE Vector Graphic - Fill","hd":false},{"ty":"tr","p":{"a":0,"k":[0,0],"ix":2},"a":{"a":0,"k":[0,0],"ix":1},"s":{"a":0,"k":[100,100],"ix":3},"r":{"a":0,"k":0,"ix":6},"o":{"a":0,"k":100,"ix":7},"sk":{"a":0,"k":0,"ix":4},"sa":{"a":0,"k":0,"ix":5},"nm":"Transform"}],"nm":"Rectangle 1141","np":3,"cix":2,"bm":0,"ix":1,"mn":"ADBE Vector Group","hd":false}],"ip":0,"op":3600,"st":0,"bm":0},{"ddd":0,"ind":50,"ty":4,"nm":"Rectangle 1140","parent":47,"sr":1,"ks":{"o":{"a":0,"k":100,"ix":11},"r":{"a":0,"k":0,"ix":10},"p":{"a":0,"k":[-0.138,-5.578,0],"ix":2,"l":2},"a":{"a":0,"k":[0,0,0],"ix":1,"l":2},"s":{"a":0,"k":[100,100,100],"ix":6,"l":2}},"ao":0,"shapes":[{"ty":"gr","it":[{"ty":"rc","d":1,"s":{"a":0,"k":[36.188,12.636],"ix":2},"p":{"a":0,"k":[0,0],"ix":3},"r":{"a":0,"k":0.5,"ix":4},"nm":"Rectangle Path 1","mn":"ADBE Vector Shape - Rect","hd":false},{"ty":"st","c":{"a":0,"k":[0.694117647059,0.396078431373,0.290196078431,1],"ix":3},"o":{"a":0,"k":100,"ix":4},"w":{"a":0,"k":1,"ix":5},"lc":1,"lj":1,"ml":4,"bm":0,"nm":"Stroke 1","mn":"ADBE Vector Graphic - Stroke","hd":false},{"ty":"fl","c":{"a":0,"k":[1,0.533333333333,0.372549019608,1],"ix":4},"o":{"a":0,"k":100,"ix":5},"r":1,"bm":0,"nm":"Fill 1","mn":"ADBE Vector Graphic - Fill","hd":false},{"ty":"tr","p":{"a":0,"k":[0,0],"ix":2},"a":{"a":0,"k":[0,0],"ix":1},"s":{"a":0,"k":[100,100],"ix":3},"r":{"a":0,"k":0,"ix":6},"o":{"a":0,"k":100,"ix":7},"sk":{"a":0,"k":0,"ix":4},"sa":{"a":0,"k":0,"ix":5},"nm":"Transform"}],"nm":"Rectangle 1140","np":3,"cix":2,"bm":0,"ix":1,"mn":"ADBE Vector Group","hd":false}],"ip":0,"op":3600,"st":0,"bm":0},{"ddd":0,"ind":51,"ty":4,"nm":"Rectangle 1139","parent":47,"sr":1,"ks":{"o":{"a":0,"k":100,"ix":11},"r":{"a":0,"k":0,"ix":10},"p":{"a":0,"k":[0.138,-0.023,0],"ix":2,"l":2},"a":{"a":0,"k":[0,0,0],"ix":1,"l":2},"s":{"a":0,"k":[100,100,100],"ix":6,"l":2}},"ao":0,"shapes":[{"ty":"gr","it":[{"ty":"rc","d":1,"s":{"a":0,"k":[36.188,23.793],"ix":2},"p":{"a":0,"k":[0,0],"ix":3},"r":{"a":0,"k":3.5,"ix":4},"nm":"Rectangle Path 1","mn":"ADBE Vector Shape - Rect","hd":false},{"ty":"st","c":{"a":0,"k":[0.694117647059,0.396078431373,0.290196078431,1],"ix":3},"o":{"a":0,"k":100,"ix":4},"w":{"a":0,"k":1,"ix":5},"lc":1,"lj":1,"ml":4,"bm":0,"nm":"Stroke 1","mn":"ADBE Vector Graphic - Stroke","hd":false},{"ty":"fl","c":{"a":0,"k":[1,0.533333333333,0.372549019608,1],"ix":4},"o":{"a":0,"k":100,"ix":5},"r":1,"bm":0,"nm":"Fill 1","mn":"ADBE Vector Graphic - Fill","hd":false},{"ty":"tr","p":{"a":0,"k":[0,0],"ix":2},"a":{"a":0,"k":[0,0],"ix":1},"s":{"a":0,"k":[100,100],"ix":3},"r":{"a":0,"k":0,"ix":6},"o":{"a":0,"k":100,"ix":7},"sk":{"a":0,"k":0,"ix":4},"sa":{"a":0,"k":0,"ix":5},"nm":"Transform"}],"nm":"Rectangle 1139","np":3,"cix":2,"bm":0,"ix":1,"mn":"ADBE Vector Group","hd":false}],"ip":0,"op":3600,"st":0,"bm":0},{"ddd":0,"ind":52,"ty":4,"nm":"Rectangle 1138","parent":47,"sr":1,"ks":{"o":{"a":0,"k":100,"ix":11},"r":{"a":0,"k":0,"ix":10},"p":{"a":0,"k":[-0.138,4.959,0],"ix":2,"l":2},"a":{"a":0,"k":[0,0,0],"ix":1,"l":2},"s":{"a":0,"k":[100,100,100],"ix":6,"l":2}},"ao":0,"shapes":[{"ty":"gr","it":[{"ty":"rc","d":1,"s":{"a":0,"k":[36.188,23.793],"ix":2},"p":{"a":0,"k":[0,0],"ix":3},"r":{"a":0,"k":3.5,"ix":4},"nm":"Rectangle Path 1","mn":"ADBE Vector Shape - Rect","hd":false},{"ty":"st","c":{"a":0,"k":[0.694117647059,0.396078431373,0.290196078431,1],"ix":3},"o":{"a":0,"k":100,"ix":4},"w":{"a":0,"k":1,"ix":5},"lc":1,"lj":1,"ml":4,"bm":0,"nm":"Stroke 1","mn":"ADBE Vector Graphic - Stroke","hd":false},{"ty":"fl","c":{"a":0,"k":[1,0.533333333333,0.372549019608,1],"ix":4},"o":{"a":0,"k":100,"ix":5},"r":1,"bm":0,"nm":"Fill 1","mn":"ADBE Vector Graphic - Fill","hd":false},{"ty":"tr","p":{"a":0,"k":[0,0],"ix":2},"a":{"a":0,"k":[0,0],"ix":1},"s":{"a":0,"k":[100,100],"ix":3},"r":{"a":0,"k":0,"ix":6},"o":{"a":0,"k":100,"ix":7},"sk":{"a":0,"k":0,"ix":4},"sa":{"a":0,"k":0,"ix":5},"nm":"Transform"}],"nm":"Rectangle 1138","np":3,"cix":2,"bm":0,"ix":1,"mn":"ADBE Vector Group","hd":false}],"ip":0,"op":3600,"st":0,"bm":0},{"ddd":0,"ind":53,"ty":4,"nm":"Rectangle 1137","parent":47,"sr":1,"ks":{"o":{"a":0,"k":100,"ix":11},"r":{"a":0,"k":0,"ix":10},"p":{"a":0,"k":[-0.138,1.86,0],"ix":2,"l":2},"a":{"a":0,"k":[0,0,0],"ix":1,"l":2},"s":{"a":0,"k":[100,100,100],"ix":6,"l":2}},"ao":0,"shapes":[{"ty":"gr","it":[{"ty":"rc","d":1,"s":{"a":0,"k":[36.188,27.513],"ix":2},"p":{"a":0,"k":[0,0],"ix":3},"r":{"a":0,"k":3.5,"ix":4},"nm":"Rectangle Path 1","mn":"ADBE Vector Shape - Rect","hd":false},{"ty":"st","c":{"a":0,"k":[0.694117647059,0.396078431373,0.290196078431,1],"ix":3},"o":{"a":0,"k":100,"ix":4},"w":{"a":0,"k":1,"ix":5},"lc":1,"lj":1,"ml":4,"bm":0,"nm":"Stroke 1","mn":"ADBE Vector Graphic - Stroke","hd":false},{"ty":"fl","c":{"a":0,"k":[1,0.533333333333,0.376470588235,1],"ix":4},"o":{"a":0,"k":100,"ix":5},"r":1,"bm":0,"nm":"Fill 1","mn":"ADBE Vector Graphic - Fill","hd":false},{"ty":"tr","p":{"a":0,"k":[0,0],"ix":2},"a":{"a":0,"k":[0,0],"ix":1},"s":{"a":0,"k":[100,100],"ix":3},"r":{"a":0,"k":0,"ix":6},"o":{"a":0,"k":100,"ix":7},"sk":{"a":0,"k":0,"ix":4},"sa":{"a":0,"k":0,"ix":5},"nm":"Transform"}],"nm":"Rectangle 1137","np":3,"cix":2,"bm":0,"ix":1,"mn":"ADBE Vector Group","hd":false}],"ip":0,"op":3600,"st":0,"bm":0},{"ddd":0,"ind":54,"ty":4,"nm":"Union 9","parent":1,"sr":1,"ks":{"o":{"a":0,"k":100,"ix":11},"r":{"a":0,"k":0,"ix":10},"p":{"a":0,"k":[-6.877,-2.789,0],"ix":2,"l":2},"a":{"a":0,"k":[175.715,124.897,0],"ix":1,"l":2},"s":{"a":0,"k":[100,100,100],"ix":6,"l":2}},"ao":0,"shapes":[{"ty":"gr","it":[{"ind":0,"ty":"sh","ix":1,"ks":{"a":0,"k":{"i":[[0,0],[0,0]],"o":[[0,0],[0,0]],"v":[[286.97,249.793],[298.746,249.793]],"c":true},"ix":2},"nm":"Path 1","mn":"ADBE Vector Shape - Group","hd":false},{"ind":1,"ty":"sh","ix":2,"ks":{"a":0,"k":{"i":[[0,0],[0,0]],"o":[[0,0],[0,0]],"v":[[85.532,249.793],[269.616,249.793]],"c":true},"ix":2},"nm":"Path 2","mn":"ADBE Vector Shape - Group","hd":false},{"ind":2,"ty":"sh","ix":3,"ks":{"a":0,"k":{"i":[[0,0],[0,0]],"o":[[0,0],[0,0]],"v":[[155.57,235.537],[324.159,235.537]],"c":true},"ix":2},"nm":"Path 3","mn":"ADBE Vector Shape - Group","hd":false},{"ind":3,"ty":"sh","ix":4,"ks":{"a":0,"k":{"i":[[0,0],[0,0]],"o":[[0,0],[0,0]],"v":[[132.018,235.537],[141.315,235.537]],"c":true},"ix":2},"nm":"Path 4","mn":"ADBE Vector Shape - Group","hd":false},{"ind":4,"ty":"sh","ix":5,"ks":{"a":0,"k":{"i":[[0,0],[0,0]],"o":[[0,0],[0,0]],"v":[[52.064,235.537],[61.981,235.537]],"c":true},"ix":2},"nm":"Path 5","mn":"ADBE Vector Shape - Group","hd":false},{"ind":5,"ty":"sh","ix":6,"ks":{"a":0,"k":{"i":[[0,0],[0,0]],"o":[[0,0],[0,0]],"v":[[14.256,235.537],[43.386,235.537]],"c":true},"ix":2},"nm":"Path 6","mn":"ADBE Vector Shape - Group","hd":false},{"ind":6,"ty":"sh","ix":7,"ks":{"a":0,"k":{"i":[[0,0],[-1.487,0]],"o":[[14.669,0],[0,0]],"v":[[26.032,223.141],[71.897,223.141]],"c":true},"ix":2},"nm":"Path 7","mn":"ADBE Vector Shape - Group","hd":false},{"ind":7,"ty":"sh","ix":8,"ks":{"a":0,"k":{"i":[[0,0],[0,0]],"o":[[0,0],[0,0]],"v":[[0,223.141],[14.256,223.141]],"c":true},"ix":2},"nm":"Path 8","mn":"ADBE Vector Shape - Group","hd":false},{"ind":8,"ty":"sh","ix":9,"ks":{"a":0,"k":{"i":[[0,0],[0,0]],"o":[[0,0],[0,0]],"v":[[226.823,222.644],[233.022,222.644]],"c":true},"ix":2},"nm":"Path 9","mn":"ADBE Vector Shape - Group","hd":false},{"ind":9,"ty":"sh","ix":10,"ks":{"a":0,"k":{"i":[[0,0],[0,0]],"o":[[0,0],[0,0]],"v":[[186.536,222.644],[216.906,222.644]],"c":true},"ix":2},"nm":"Path 10","mn":"ADBE Vector Shape - Group","hd":false},{"ind":10,"ty":"sh","ix":11,"ks":{"a":0,"k":{"i":[[0,0],[0,0]],"o":[[0,0],[0,0]],"v":[[172.925,215.702],[180.984,215.702]],"c":true},"ix":2},"nm":"Path 11","mn":"ADBE Vector Shape - Group","hd":false},{"ind":11,"ty":"sh","ix":12,"ks":{"a":0,"k":{"i":[[0,0],[0,0]],"o":[[0,0],[0,0]],"v":[[314.242,104.133],[334.076,104.133]],"c":true},"ix":2},"nm":"Path 12","mn":"ADBE Vector Shape - Group","hd":false},{"ind":12,"ty":"sh","ix":13,"ks":{"a":0,"k":{"i":[[0,0],[0,0]],"o":[[0,0],[0,0]],"v":[[292.549,91.735],[351.43,91.735]],"c":true},"ix":2},"nm":"Path 13","mn":"ADBE Vector Shape - Group","hd":false},{"ind":13,"ty":"sh","ix":14,"ks":{"a":0,"k":{"i":[[0,0],[0,0]],"o":[[0,0],[0,0]],"v":[[311.763,29.751],[317.34,29.751]],"c":true},"ix":2},"nm":"Path 14","mn":"ADBE Vector Shape - Group","hd":false},{"ind":14,"ty":"sh","ix":15,"ks":{"a":0,"k":{"i":[[0,0],[0,0]],"o":[[0,0],[0,0]],"v":[[285.73,29.751],[301.225,29.751]],"c":true},"ix":2},"nm":"Path 15","mn":"ADBE Vector Shape - Group","hd":false},{"ind":15,"ty":"sh","ix":16,"ks":{"a":0,"k":{"i":[[0,0],[0,0]],"o":[[0,0],[0,0]],"v":[[275.193,17.975],[324.158,17.975]],"c":true},"ix":2},"nm":"Path 16","mn":"ADBE Vector Shape - Group","hd":false},{"ind":16,"ty":"sh","ix":17,"ks":{"a":0,"k":{"i":[[0,0],[0,0]],"o":[[0,0],[0,0]],"v":[[15.494,14.876],[96.69,14.876]],"c":true},"ix":2},"nm":"Path 17","mn":"ADBE Vector Shape - Group","hd":false},{"ind":17,"ty":"sh","ix":18,"ks":{"a":0,"k":{"i":[[0,0],[0,0]],"o":[[0,0],[0,0]],"v":[[57.641,1.238],[106.605,1.238]],"c":true},"ix":2},"nm":"Path 18","mn":"ADBE Vector Shape - Group","hd":false},{"ind":18,"ty":"sh","ix":19,"ks":{"a":0,"k":{"i":[[0,0],[0,0]],"o":[[0,0],[0,0]],"v":[[117.762,0],[128.299,0]],"c":true},"ix":2},"nm":"Path 19","mn":"ADBE Vector Shape - Group","hd":false},{"ty":"st","c":{"a":0,"k":[0.694117647059,0.396078431373,0.290196078431,1],"ix":3},"o":{"a":0,"k":100,"ix":4},"w":{"a":0,"k":2,"ix":5},"lc":2,"lj":1,"ml":4,"bm":0,"nm":"Stroke 1","mn":"ADBE Vector Graphic - Stroke","hd":false},{"ty":"tr","p":{"a":0,"k":[0,0],"ix":2},"a":{"a":0,"k":[0,0],"ix":1},"s":{"a":0,"k":[100,100],"ix":3},"r":{"a":0,"k":0,"ix":6},"o":{"a":0,"k":100,"ix":7},"sk":{"a":0,"k":0,"ix":4},"sa":{"a":0,"k":0,"ix":5},"nm":"Transform"}],"nm":"Union 9","np":21,"cix":2,"bm":0,"ix":1,"mn":"ADBE Vector Group","hd":false},{"ty":"tm","s":{"a":0,"k":0,"ix":1},"e":{"a":1,"k":[{"i":{"x":[0.667],"y":[1]},"o":{"x":[0.333],"y":[0]},"t":0,"s":[0]},{"t":60,"s":[100]}],"ix":2},"o":{"a":0,"k":0,"ix":3},"m":1,"ix":2,"nm":"Trim Paths 1","mn":"ADBE Vector Filter - Trim","hd":false}],"ip":0,"op":121,"st":0,"bm":0},{"ddd":0,"ind":55,"ty":4,"nm":"Group 826","parent":1,"sr":1,"ks":{"o":{"a":0,"k":100,"ix":11},"r":{"a":0,"k":0,"ix":10},"p":{"a":0,"k":[-128.051,15.496,0],"ix":2,"l":2},"a":{"a":0,"k":[0,0,0],"ix":1,"l":2},"s":{"a":0,"k":[100,100,100],"ix":6,"l":2}},"ao":0,"shapes":[{"ty":"rc","d":1,"s":{"a":0,"k":[145.035,145.042],"ix":2},"p":{"a":0,"k":[0,0],"ix":3},"r":{"a":0,"k":0,"ix":4},"nm":"Rectangle Path 1","mn":"ADBE Vector Shape - Rect","hd":false}],"ip":0,"op":3600,"st":0,"bm":0},{"ddd":0,"ind":56,"ty":4,"nm":"Path 2711","parent":55,"sr":1,"ks":{"o":{"a":0,"k":100,"ix":11},"r":{"a":0,"k":0,"ix":10},"p":{"a":0,"k":[0.42,0.725,0],"ix":2,"l":2},"a":{"a":0,"k":[13.396,13.397,0],"ix":1,"l":2},"s":{"a":0,"k":[100,100,100],"ix":6,"l":2}},"ao":0,"shapes":[{"ty":"gr","it":[{"ind":0,"ty":"sh","ix":1,"ks":{"a":0,"k":{"i":[[0,0],[0,0]],"o":[[0,0],[0,0]],"v":[[12.503,26.794],[12.503,0]],"c":false},"ix":2},"nm":"Path 1","mn":"ADBE Vector Shape - Group","hd":false},{"ind":1,"ty":"sh","ix":2,"ks":{"a":0,"k":{"i":[[0,0],[0,0]],"o":[[0,0],[0,0]],"v":[[0,12.504],[26.793,12.504]],"c":false},"ix":2},"nm":"Path 2","mn":"ADBE Vector Shape - Group","hd":false},{"ty":"st","c":{"a":0,"k":[1,1,1,1],"ix":3},"o":{"a":0,"k":100,"ix":4},"w":{"a":0,"k":2,"ix":5},"lc":2,"lj":1,"ml":4,"bm":0,"nm":"Stroke 1","mn":"ADBE Vector Graphic - Stroke","hd":false},{"ty":"tr","p":{"a":0,"k":[0,0],"ix":2},"a":{"a":0,"k":[0,0],"ix":1},"s":{"a":0,"k":[100,100],"ix":3},"r":{"a":0,"k":0,"ix":6},"o":{"a":0,"k":100,"ix":7},"sk":{"a":0,"k":0,"ix":4},"sa":{"a":0,"k":0,"ix":5},"nm":"Transform"}],"nm":"Path 2711","np":4,"cix":2,"bm":0,"ix":1,"mn":"ADBE Vector Group","hd":false}],"ip":0,"op":3600,"st":0,"bm":0},{"ddd":0,"ind":57,"ty":4,"nm":"Path 2671","parent":55,"sr":1,"ks":{"o":{"a":0,"k":100,"ix":11},"r":{"a":0,"k":0,"ix":10},"p":{"a":0,"k":[-0.077,0.23,0],"ix":2,"l":2},"a":{"a":0,"k":[60.524,60.527,0],"ix":1,"l":2},"s":{"a":0,"k":[100,100,100],"ix":6,"l":2}},"ao":0,"shapes":[{"ty":"gr","it":[{"ind":0,"ty":"sh","ix":1,"ks":{"a":0,"k":{"i":[[0,-33.428],[33.427,0],[0,33.428],[-33.427,0]],"o":[[0,33.428],[-33.427,0],[0,-33.428],[33.427,0]],"v":[[121.049,60.527],[60.524,121.054],[0,60.527],[60.524,0]],"c":true},"ix":2},"nm":"Path 1","mn":"ADBE Vector Shape - Group","hd":false},{"ty":"st","c":{"a":0,"k":[0.694117647059,0.396078431373,0.290196078431,1],"ix":3},"o":{"a":0,"k":100,"ix":4},"w":{"a":0,"k":2,"ix":5},"lc":1,"lj":1,"ml":4,"bm":0,"nm":"Stroke 1","mn":"ADBE Vector Graphic - Stroke","hd":false},{"ty":"gf","o":{"a":0,"k":100,"ix":10},"r":1,"bm":0,"g":{"p":3,"k":{"a":0,"k":[0,1,0.533,0.376,0.5,1,0.741,0.441,1,1,0.949,0.506],"ix":9}},"s":{"a":0,"k":[51,0],"ix":5},"e":{"a":0,"k":[214,0],"ix":6},"t":1,"nm":"Gradient Fill 1","mn":"ADBE Vector Graphic - G-Fill","hd":false},{"ty":"tr","p":{"a":0,"k":[0,0],"ix":2},"a":{"a":0,"k":[0,0],"ix":1},"s":{"a":0,"k":[100,100],"ix":3},"r":{"a":0,"k":0,"ix":6},"o":{"a":0,"k":100,"ix":7},"sk":{"a":0,"k":0,"ix":4},"sa":{"a":0,"k":0,"ix":5},"nm":"Transform"}],"nm":"Path 2671","np":3,"cix":2,"bm":0,"ix":1,"mn":"ADBE Vector Group","hd":false}],"ip":0,"op":3600,"st":0,"bm":0},{"ddd":0,"ind":58,"ty":4,"nm":"Ellipse 121","parent":55,"sr":1,"ks":{"o":{"a":0,"k":100,"ix":11},"r":{"a":0,"k":0,"ix":10},"p":{"a":0,"k":[0,0,0],"ix":2,"l":2},"a":{"a":0,"k":[0,0,0],"ix":1,"l":2},"s":{"a":0,"k":[100,100,100],"ix":6,"l":2}},"ao":0,"shapes":[{"ty":"gr","it":[{"d":1,"ty":"el","s":{"a":0,"k":[145.035,145.042],"ix":2},"p":{"a":0,"k":[0,0],"ix":3},"nm":"Ellipse Path 1","mn":"ADBE Vector Shape - Ellipse","hd":false},{"ty":"fl","c":{"a":0,"k":[0.694117647059,0.396078431373,0.294117647059,1],"ix":4},"o":{"a":0,"k":100,"ix":5},"r":1,"bm":0,"nm":"Fill 1","mn":"ADBE Vector Graphic - Fill","hd":false},{"ty":"tr","p":{"a":0,"k":[0,0],"ix":2},"a":{"a":0,"k":[0,0],"ix":1},"s":{"a":0,"k":[100,100],"ix":3},"r":{"a":0,"k":0,"ix":6},"o":{"a":0,"k":100,"ix":7},"sk":{"a":0,"k":0,"ix":4},"sa":{"a":0,"k":0,"ix":5},"nm":"Transform"}],"nm":"Ellipse 121","np":3,"cix":2,"bm":0,"ix":1,"mn":"ADBE Vector Group","hd":false}],"ip":0,"op":3600,"st":0,"bm":0}],"markers":[]}